<?xml version="1.0" encoding="utf-8" ?> 
<LANG type="utf-8" descript="German">
    <!-- German Language XML file -->
    <!-- ##### LOGIN PAGE ##### -->
    <LOGIN_USER_LOGIN>Login</LOGIN_USER_LOGIN>
    <LOGIN_ACCOUNT>Benutzername</LOGIN_ACCOUNT>
    <LOGIN_PASSWORD>Passwort</LOGIN_PASSWORD>
    <LOGIN_LANGUAGE>Sprache</LOGIN_LANGUAGE>
    <LOGIN_ACCOUNT_ERR>Benutzername ist leer.</LOGIN_ACCOUNT_ERR>
    <LOGIN_PASSWORD_ERR>Passwort ist leer</LOGIN_PASSWORD_ERR>
    <LOGIN_ERROR>Benutzername/Passwort falsch.</LOGIN_ERROR>
    <!-- ##### BUTTONs ##### -->
    <BUTTON_LOGIN>Login</BUTTON_LOGIN>
    <BUTTON_APPLY>Übernehmen</BUTTON_APPLY>
    <BUTTON_RESET>Zurücksetzen</BUTTON_RESET>
    <BUTTON_GET>Abrufen</BUTTON_GET>
    <BUTTON_EDIT>Verändern</BUTTON_EDIT>
    <BUTTON_TEST>Testen</BUTTON_TEST>
    <BUTTON_UPLOAD>Upload</BUTTON_UPLOAD>
    <BUTTON_REMOVE>Entfernen</BUTTON_REMOVE>
    <BUTTON_FTPd>FTP-Server-Konfiguration</BUTTON_FTPd>
    <BUTTON_SMTP>SMTP-Server-Konfiguration</BUTTON_SMTP>
    <BUTTON_HTTPd1>HTTP-Server 1-Konfiguration</BUTTON_HTTPd1>
    <BUTTON_HTTPd2>HTTP-Server 2-Konfiguration</BUTTON_HTTPd2>
    <BUTTON_SAVE>Sichern</BUTTON_SAVE>
    <BUTTON_CANCEL>Abbrech.</BUTTON_CANCEL>
    <!-- ##### COMMON MESSAGE ##### -->
    <COMMON_MSG_NEED_SAVE_REBOOT>* Neueinstellung wird erst nach "Sichern &amp; Neustart" aktiv.</COMMON_MSG_NEED_SAVE_REBOOT>
    <COMMON_ALERT_NEED_SAVE_REBOOT>* Einstellungen werden nach "Sichern &amp; Neustart" aktiv.</COMMON_ALERT_NEED_SAVE_REBOOT>
    <COMMOM_MSG_ENABLED>Aktiviert</COMMOM_MSG_ENABLED>
    <COMMON_MSG_NETADDR_ERR>Ungültige IP-Adresse.</COMMON_MSG_NETADDR_ERR>
    <COMMOM_MSG_NETMASK_ERR>Subnet-Maske falsch.</COMMOM_MSG_NETMASK_ERR>
    <REMOVE_FILE_ALERT>Möchten Sie diese Datei löschen?</REMOVE_FILE_ALERT>
    <COMMON_MSG_SET_ERR>Fehler. Ungültige Einstellungen.</COMMON_MSG_SET_ERR>
    <COMMON_MSG_SPEED>Speed</COMMON_MSG_SPEED>
    <COMMON_MSG_STEP_SIZES>Schrittgröße</COMMON_MSG_STEP_SIZES>
    <COMMON_MSG_MODE>Modus</COMMON_MSG_MODE>
    <COMMON_MSG_NUM>Zahl</COMMON_MSG_NUM>
    <COMMON_MSG_NAME>Name</COMMON_MSG_NAME>
    <COMMON_MSG_REMOVE>Entfernen</COMMON_MSG_REMOVE>
    <COMMON_MSG_DWELL>Verweildauer</COMMON_MSG_DWELL>
    <COMMON_MSG_ADD>Hinzufü.</COMMON_MSG_ADD>
    <COMMON_MSG_TOP>Top</COMMON_MSG_TOP>
    <COMMON_MSG_BOTTOM>Boden</COMMON_MSG_BOTTOM>
    <COMMON_MSG_SECONDS>Sekunden</COMMON_MSG_SECONDS>
    <COMMON_MSG_CHANNEL>Kanal</COMMON_MSG_CHANNEL>
    <COMMON_MSG_START>Beginn</COMMON_MSG_START>
    <COMMON_MSG_STOP>Stop</COMMON_MSG_STOP>
    <COMMON_MSG_RESUME>Fortsetzen</COMMON_MSG_RESUME>
    <COMMON_MSG_END>Ende</COMMON_MSG_END>
    <COMMON_MSG_AUTO>Auto</COMMON_MSG_AUTO>
    <COMMON_MSG_REGION1>Bereich 1</COMMON_MSG_REGION1>
    <COMMON_MSG_REGION2>Bereich 2</COMMON_MSG_REGION2>
    <COMMON_MSG_REGION3>Bereich 3</COMMON_MSG_REGION3>
    <COMMON_MSG_REGION4>Bereich 4</COMMON_MSG_REGION4>
    <COMMON_MSG_REGION5>Bereich 5</COMMON_MSG_REGION5>
    <COMMON_MSG_REGION6>Bereich 6</COMMON_MSG_REGION6>
    <COMMON_MSG_REGION7>Bereich 7</COMMON_MSG_REGION7>
    <COMMON_MSG_REGION8>Bereich 8</COMMON_MSG_REGION8>
    <COMMON_MSG_REGION9>Bereich 9</COMMON_MSG_REGION9>
    <COMMON_MSG_REGION10>Bereich 10</COMMON_MSG_REGION10>
    <!-- ##### COMMON SETTING VALUES ##### -->
    <COMMON_SETTING_VALUE_LOWEST>kleinster</COMMON_SETTING_VALUE_LOWEST>
    <COMMON_SETTING_VALUE_LOW>klein</COMMON_SETTING_VALUE_LOW>
    <COMMON_SETTING_VALUE_MEDIUM>medium</COMMON_SETTING_VALUE_MEDIUM>
    <COMMON_SETTING_VALUE_HIGH>hoch</COMMON_SETTING_VALUE_HIGH>
    <COMMON_SETTING_VALUE_HIGHEST>höchster</COMMON_SETTING_VALUE_HIGHEST>
    <!-- ##### LIVE VIEW PAGE ##### -->
    <LIVEVIEW_LIVE>Live</LIVEVIEW_LIVE>
    <LIVEVIEW_SETUP>Setup</LIVEVIEW_SETUP>
    <LIVE_FUNCTION>Funktion</LIVE_FUNCTION>
    <LIVE_MEDIA>Media</LIVE_MEDIA>
    <LIVE_STREAM_TYPE>Encoder</LIVE_STREAM_TYPE>
    <LIVE_SIZE>Größe</LIVE_SIZE>
    <LIVE_DO1>DO1</LIVE_DO1>
    <LIVE_DO2>DO2</LIVE_DO2>
    <!-- ##### MENU PAGE ##### -->
    <HEAD_LIVE>Live</HEAD_LIVE>
    <HEAD_SETUP>Setup</HEAD_SETUP>
    <MENU_HOST>Host</MENU_HOST>
    <MENU_HOST_DATE_TIME>Datum &amp; Uhrzeit</MENU_HOST_DATE_TIME>
    <MENU_NETWORK>Netzwerk</MENU_NETWORK>
    <MENU_NETWORK_IP_FILTER>IP-Filter</MENU_NETWORK_IP_FILTER>
    <MENU_NETWORK_PORT_MAPPING>Port Mapping</MENU_NETWORK_PORT_MAPPING>
    <MENU_NETWORK_TOS>ToS</MENU_NETWORK_TOS>
    <MENU_NETWORK_UPnP>UPnP™</MENU_NETWORK_UPnP>
    <MENU_NETWORK_SNMP>SNMP-Einstellung</MENU_NETWORK_SNMP>
    <MENU_NETWORK_RTP>RTP</MENU_NETWORK_RTP>
    <MENU_NETWORK_BONJOUR>Bonjour</MENU_NETWORK_BONJOUR>
    <MENU_NETWORK_8021X>IEEE 802.1X</MENU_NETWORK_8021X>
    <MENU_NETWORK_LINK_SPEED>Speed &amp; Duplex</MENU_NETWORK_LINK_SPEED>
    <MENU_IP_SETTINGS>IP-Einstellungen</MENU_IP_SETTINGS>
    <MENU_NETWORK_CONNECTION_TYPE>Verbindungsart</MENU_NETWORK_CONNECTION_TYPE>
    <MENU_NETWORK_DNS>DNS</MENU_NETWORK_DNS>
    <MENU_NETWORK_DDNS>DDNS</MENU_NETWORK_DDNS>
    <MENU_VIDEO_AND_AUDIO>Video &amp; Audio</MENU_VIDEO_AND_AUDIO>
    <MENU_VIDEO_AND_AUDIO_ADVANCE>Video </MENU_VIDEO_AND_AUDIO_ADVANCE>
    <MENU_VIDEO_AUDIO>Audio</MENU_VIDEO_AUDIO>
    <MENU_VIDEO_AND_AUDIO_PRIVACE_MASK>OSD/Privacy Mask</MENU_VIDEO_AND_AUDIO_PRIVACE_MASK>
    <MENU_EVENT>Ereignis</MENU_EVENT>
    <MENU_EVENT_SERVER>Ereignis-Server</MENU_EVENT_SERVER>
    <MENU_EVENT_CONFIGURATOR>Ereignis-Setup</MENU_EVENT_CONFIGURATOR>
    <MENU_EVENT_LIST>Ereignis-Liste</MENU_EVENT_LIST>
    <MENU_EVENT_MANUAL>Man. Ereignis</MENU_EVENT_MANUAL>
    <MENU_SYSTEM>System</MENU_SYSTEM>
    <MENU_USER_SETTING>Benutzerkonto</MENU_USER_SETTING>
    <MENU_MAINTAIN_SYSTEM_INFO>System-Info</MENU_MAINTAIN_SYSTEM_INFO>
    <MENU_MAINTAIN_FACTORY_DEFAULT>Werkseinstellung</MENU_MAINTAIN_FACTORY_DEFAULT>
    <MENU_MAINTAIN_FIRMWARE_UPGRADE>Firmware-Upload</MENU_MAINTAIN_FIRMWARE_UPGRADE>
    <MENU_MAINTAIN_SAVE_AND_REBOOT>Sichern &amp; Neustart</MENU_MAINTAIN_SAVE_AND_REBOOT>
    <MENU_MAINTAIN_LOGOUT>Logout</MENU_MAINTAIN_LOGOUT>
    <!-- ##### HOST PAGE ##### -->
    <SETTING_HOST_HOST>Host</SETTING_HOST_HOST>
    <SETTING_HOST_HOST_NAME>Host-Name</SETTING_HOST_HOST_NAME>
    <SETTING_HOST_LANGUAGE>Sprache</SETTING_HOST_LANGUAGE>
    <SETTING_HOST_CAMERA_NAME>Kamera-Name</SETTING_HOST_CAMERA_NAME>
    <SETTING_HOST_SERIAL_SETTING>Serielle Einstellung</SETTING_HOST_SERIAL_SETTING>
    <SETTING_HOST_SERIAL_PORT>Serial Port</SETTING_HOST_SERIAL_PORT>
    <SETTING_HOST_SERIAL_PORT_CONTROL>Serial Port Control</SETTING_HOST_SERIAL_PORT_CONTROL>
    <SETTING_HOST_SERIAL_PORT_BAUD_RATE>Serial Port Baud Rate</SETTING_HOST_SERIAL_PORT_BAUD_RATE>
    <SETTING_HOST_CNAME_EMPTY>Kamera-Name muss vergeben werden.</SETTING_HOST_CNAME_EMPTY>
    <SETTING_HOST_NAME_ERR>
        Regel für Geräte Name.&#10;
        1. Nur A~Z, a~z, 0~9, Minus Zeichen (-) und Punkte (.) sind erlaubt.&#10;
        2. Kein leeres oder Space Zeichen als Teil des Namens benutzen.&#10;
        3. Der letzte Buchstabe darf kein Minus Zeichen oder Punkt sein.&#10;
        4. Ein Buchstaben Namen sind nicht erlaubt.&#10;
        5. Das erste Zeichen darf ein Buchstabe oder Zahl sein. 
    </SETTING_HOST_NAME_ERR>
    <SETTING_HOST_NAME_EMPTY>Host-Name muss vergeben werden.</SETTING_HOST_NAME_EMPTY>
    <!-- ##### DATE and TIME PAGE ##### -->
    <SETTING_DATE_TIME_SETTING>Einstellung des Datums</SETTING_DATE_TIME_SETTING>
    <SETTING_DATE_TIME_SNTP_NTP_SERVER>SNTP/NTP-Server</SETTING_DATE_TIME_SNTP_NTP_SERVER>
    <SETTING_DATE_TIME_IP_ADDRESS>IP-Adresse</SETTING_DATE_TIME_IP_ADDRESS>
    <SETTING_DATE_TIME_SYNC_TIME>Synchr.-Intervall</SETTING_DATE_TIME_SYNC_TIME>
    <SETTING_DATE_TIME_SET_MANUALLY>Manuell einstellen</SETTING_DATE_TIME_SET_MANUALLY>
    <SETTING_DATE_TIME_DATE>Datum</SETTING_DATE_TIME_DATE>
    <SETTING_DATE_TIME_TIME>Zeit</SETTING_DATE_TIME_TIME>
    <SETTING_DATE_TIME_TIME_ZONE>Zeitzone</SETTING_DATE_TIME_TIME_ZONE>
    <SETTING_DATE_TIME_DAY_LIGHT_SAVING>Sommerzeit/Winterzeit</SETTING_DATE_TIME_DAY_LIGHT_SAVING>
    <SETTING_DATE_TIME_START_TIME>Beginn</SETTING_DATE_TIME_START_TIME>
    <SETTING_DATE_TIME_END_TIME>Ende</SETTING_DATE_TIME_END_TIME>
    <!-- ##### NETWORK - IP ADDRESS FILTERING PAGE ##### -->
    <SETTING_IP_FILTER>IP-Adressfilter</SETTING_IP_FILTER>
    <SETTING_IP_FILTER_STATUS>Aktiviert</SETTING_IP_FILTER_STATUS>
    <SETTING_IP_FILTER_IP>IP-Adresseinstellung</SETTING_IP_FILTER_IP>
    <SETTING_IP_FILTER_TYPE>IP-Adresse / Netzmaske</SETTING_IP_FILTER_TYPE>
    <SETTING_IP_FILTER_NO>Zahl</SETTING_IP_FILTER_NO>
    <SETTING_IP_FILTER_ADDRESS>IP-Adresse</SETTING_IP_FILTER_ADDRESS>
    <SETTING_IP_FILTER_MASK>Netzmaske</SETTING_IP_FILTER_MASK>
    <!-- ##### NETWORK - PORT MAPPING PAGE ##### -->
    <SETTING_PORT_MAPPING>Port Mapping</SETTING_PORT_MAPPING>
    <SETTING_PORT_MAPPING_HTTP>HTTP-Port*</SETTING_PORT_MAPPING_HTTP>
    <SETTING_PORT_MAPPING_HTTPS>HTTPS-Port*</SETTING_PORT_MAPPING_HTTPS>
    <SETTING_PORT_MAPPING_SEARCH1>Search Server-Port1</SETTING_PORT_MAPPING_SEARCH1>
    <SETTING_PORT_MAPPING_SEARCH2>Search Server-Port2</SETTING_PORT_MAPPING_SEARCH2>
    <SETTING_PORT_MAPPING_CONTROL>Control Server-Port</SETTING_PORT_MAPPING_CONTROL>
    <SETTING_PORT_MAPPING_STREAMING>Streaming Server-Port</SETTING_PORT_MAPPING_STREAMING>
    <SETTING_PORT_MAPPING_MULTICAST1>Multicast Server-Port für Media1</SETTING_PORT_MAPPING_MULTICAST1>
    <SETTING_PORT_MAPPING_MULTICAST2>Multicast Server-Port für Media2</SETTING_PORT_MAPPING_MULTICAST2>
    <SETTING_PORT_MAPPING_MULTICAST3>Multicast Server-Port für Media3</SETTING_PORT_MAPPING_MULTICAST3>
    <SETTING_PORT_MAPPING_MULTICAST4>Multicast Server-Port für Media4</SETTING_PORT_MAPPING_MULTICAST4>
    <SETTING_PORT_MAPPING_MULTICAST5>Multicast Server-Port für Media5</SETTING_PORT_MAPPING_MULTICAST5>
    <SETTING_PORT_MAPPING_MULTICAST6>Multicast Server-Port für Media6</SETTING_PORT_MAPPING_MULTICAST6>
    <SETTING_PORT_MAPPING_RTSP>RTSP Server-Port</SETTING_PORT_MAPPING_RTSP>
    <SETTING_PORT_MAPPING_RTP_VIDEO_MEDIA1>RTP Multicast Video-Port für Media1</SETTING_PORT_MAPPING_RTP_VIDEO_MEDIA1>
    <SETTING_PORT_MAPPING_RTP_AUDIO_MEDIA1>RTP Multicast Audio-Port für Media1</SETTING_PORT_MAPPING_RTP_AUDIO_MEDIA1>
    <SETTING_PORT_MAPPING_RTP_VIDEO_MEDIA2>RTP Multicast Video-Port für Media2</SETTING_PORT_MAPPING_RTP_VIDEO_MEDIA2>
    <SETTING_PORT_MAPPING_RTP_AUDIO_MEDIA2>RTP Multicast Audio-Port für Media2</SETTING_PORT_MAPPING_RTP_AUDIO_MEDIA2>
    <SETTING_PORT_MAPPING_RTP_VIDEO_MEDIA3>RTP Multicast Video-Port für Media3</SETTING_PORT_MAPPING_RTP_VIDEO_MEDIA3>
    <SETTING_PORT_MAPPING_RTP_AUDIO_MEDIA3>RTP Multicast Audio-Port für Media3</SETTING_PORT_MAPPING_RTP_AUDIO_MEDIA3>
    <SETTING_PORT_MAPPING_RTP_VIDEO_MEDIA4>RTP Multicast Video-Port für Media4</SETTING_PORT_MAPPING_RTP_VIDEO_MEDIA4>
    <SETTING_PORT_MAPPING_RTP_AUDIO_MEDIA4>RTP Multicast Audio-Port für Media4</SETTING_PORT_MAPPING_RTP_AUDIO_MEDIA4>
    <SETTING_PORT_MAPPING_RTP_VIDEO_MEDIA5>RTP Multicast Video-Port für Media5</SETTING_PORT_MAPPING_RTP_VIDEO_MEDIA5>
    <SETTING_PORT_MAPPING_RTP_AUDIO_MEDIA5>RTP Multicast Audio-Port für Media5</SETTING_PORT_MAPPING_RTP_AUDIO_MEDIA5>
    <SETTING_PORT_MAPPING_RTP_VIDEO_MEDIA6>RTP Multicast Video-Port für Media6</SETTING_PORT_MAPPING_RTP_VIDEO_MEDIA6>
    <SETTING_PORT_MAPPING_RTP_AUDIO_MEDIA6>RTP Multicast Audio-Port für Media6</SETTING_PORT_MAPPING_RTP_AUDIO_MEDIA6>
    <SETTING_PORT_MULTICAST>Multicast-Einstellungen</SETTING_PORT_MULTICAST>
    <SETTING_BY_REQUESTS>By Requests</SETTING_BY_REQUESTS>
    <SETTING_PORT_MAPPING_MULTICAST_IP>Multicast-IP</SETTING_PORT_MAPPING_MULTICAST_IP>
    <SETTING_NETWORK_PORT>Netzwerk-Port</SETTING_NETWORK_PORT>
    <SETTING_PORT_MAPPING_MULTICAST_TTL>Multicast TTL</SETTING_PORT_MAPPING_MULTICAST_TTL>
    <SETTING_PORT_MAPPING_IGMP>IGMP</SETTING_PORT_MAPPING_IGMP>
    <SETTING_PORT_MAPPING_ADDRESS_WARNING>Ungültige Multicast-IP-Adresse</SETTING_PORT_MAPPING_ADDRESS_WARNING>
    <SETTING_PORT_MAPPING_TTL_WARNING>Ungültige Multicast-TTL</SETTING_PORT_MAPPING_TTL_WARNING>
    <!-- ##### NETWORK - TOS PAGE ##### -->
    <SETTING_TOS>Type of Service</SETTING_TOS>
    <SETTING_TOS_SERVICE>Aktiviert</SETTING_TOS_SERVICE>
    <SETTING_TOS_PRIORITY>ToS-Priorität</SETTING_TOS_PRIORITY>
    <!-- ##### NETWORK - UPNP PAGE ##### -->
    <SETTING_UPnP>UPnP</SETTING_UPnP>
    <SETTING_UPnP_NAME>Friendly Name</SETTING_UPnP_NAME>
    <SETTING_UPnP_NAME_ERR>Bitte "Friendly Name" eingeben.</SETTING_UPnP_NAME_ERR>
    <!-- ##### NETWORK - SNMP PAGE ##### -->
    <SETTING_SNMP>SNMP-Einstellung</SETTING_SNMP>
    <SETTING_SNMP_ENABLED>Aktiviert</SETTING_SNMP_ENABLED>
    <SETTING_SNMP_V1V2>SNMP V1 / V2</SETTING_SNMP_V1V2>
    <SETTING_SNMP_V3>SNMP V3</SETTING_SNMP_V3>
    <SETTING_SNMP_TRAP_ENABLED>Trap aktiviert</SETTING_SNMP_TRAP_ENABLED>
    <SETTING_SNMP_V1_ENABLED>V1 aktiviert</SETTING_SNMP_V1_ENABLED>
    <SETTING_SNMP_V2_ENABLED>V2 aktiviert</SETTING_SNMP_V2_ENABLED>
    <SETTING_SNMP_READ_COMMUNITY>Read Community</SETTING_SNMP_READ_COMMUNITY>
    <SETTING_SNMP_WRITE_COMMUNITY>Write Community</SETTING_SNMP_WRITE_COMMUNITY>
    <SETTING_SNMP_SECURITY_NAME>Sicherheits-Name</SETTING_SNMP_SECURITY_NAME>
    <SETTING_SNMP_PASSWORD>Passwort</SETTING_SNMP_PASSWORD>
    <SETTING_SNMP_PASSWORD_WARNING>Passwort mit mind. 8 Zeichen</SETTING_SNMP_PASSWORD_WARNING>
    <SETTING_SNMP_DESTINATION_IP_ADDRESS>Ziel-IP-Adresse</SETTING_SNMP_DESTINATION_IP_ADDRESS>
    <SETTING_SNMP_DESTINATION_IP_ADDRESS_WARNING>IPv4-Adresse</SETTING_SNMP_DESTINATION_IP_ADDRESS_WARNING>
    <SETTING_SNMP_TRAP_COMMUNITY>Trap Community</SETTING_SNMP_TRAP_COMMUNITY>
    <SETTING_SNMP_TRAP_AVAILABLE>Vorhandene Traps</SETTING_SNMP_TRAP_AVAILABLE>
    <SETTING_SNMP_TRAP_COLD_START>Kaltstart</SETTING_SNMP_TRAP_COLD_START>
    <SETTING_SNMP_TRAP_WARN_START>Warmstart</SETTING_SNMP_TRAP_WARN_START>
    <SETTING_SNMP_TRAP_AUTHENTICATION_FAILURE>Authentifizierung gescheitert</SETTING_SNMP_TRAP_AUTHENTICATION_FAILURE>
    <SETTING_SNMP_V1V2_WANRING>SNMP V1 und/oder V2 muss aktiviert sein.</SETTING_SNMP_V1V2_WANRING>
    <SETTING_SNMP_READ_COMMUNITY_ERR>Bitte READ Community eingeben.</SETTING_SNMP_READ_COMMUNITY_ERR>
    <SETTING_SNMP_WRITE_COMMUNITY_ERR>Bitte WRITE Community eingeben.</SETTING_SNMP_WRITE_COMMUNITY_ERR>
    <SETTING_SNMP_PASSWORD_ERR>Bitte Passwort eingeben.</SETTING_SNMP_PASSWORD_ERR>
    <SETTING_SNMP_PASSWORD_LENGTH_ERR>Bitte Passwort mit mehr als 8 Zeichen eingeben.</SETTING_SNMP_PASSWORD_LENGTH_ERR>
    <SETTING_SNMP_SECURITY_NAME_ERR>Bitte Sicherheits-Namen eingeben.</SETTING_SNMP_SECURITY_NAME_ERR>
    <SETTING_SNMP_DESTINATION_IP_ADDRESS_ERR>Ungültige IP-Adresse</SETTING_SNMP_DESTINATION_IP_ADDRESS_ERR>
    <SETTING_SNMP_TRAP_COMMUNITY_ERR>Bitte Trap Community eingeben.</SETTING_SNMP_TRAP_COMMUNITY_ERR>
    <SETTING_SNMP_TRAP_AVAILABLE_ERR>Biite mind. Eine der vorhandenen Traps auswählen.</SETTING_SNMP_TRAP_AVAILABLE_ERR>
    <!-- ##### NETWORK - RTP PAGE ##### -->
    <SETTING_NETWORK_RTP>RTP</SETTING_NETWORK_RTP>
    <SETTING_RTSP_AUTHEN>RTSP-Authentifizierung</SETTING_RTSP_AUTHEN>
    <SETTING_RTP_B2>RTP B2 Frame</SETTING_RTP_B2>
    <!-- ##### NETWORK - BONJOUR PAGE ##### -->
    <SETTING_BONJOUR>Bounjour</SETTING_BONJOUR>
    <SETTING_BONJOUR_ENABLE>Aktiviert</SETTING_BONJOUR_ENABLE>
    <SETTING_BONJOUR_NAME>Friendly Name</SETTING_BONJOUR_NAME>
    <SETTING_BONJOUR_NAME_ERR>Bitte Friendly Name eingeben.</SETTING_BONJOUR_NAME_ERR>
    <!-- ##### NETWORK - IEEEE 802.1X PAGE ##### -->
    <SETTING_8021x>IEEE 802.1X*</SETTING_8021x>
    <SETTING_8021x_ENABLED>Aktiviert</SETTING_8021x_ENABLED>
    <SETTING_8021x_EAPOL_VERSION>EAPOL-Version</SETTING_8021x_EAPOL_VERSION>
    <SETTING_8021x_USERNAME>Benutzername</SETTING_8021x_USERNAME>
    <SETTING_8021x_PASSWORD>Benutzerpasswort</SETTING_8021x_PASSWORD>
    <SETTING_8021x_CA_CERTIFICATE>CA-Zertifikat</SETTING_8021x_CA_CERTIFICATE>
    <SETTING_8021x_USER_CERTIFICATE>Benutzer-Zertifikat</SETTING_8021x_USER_CERTIFICATE>
    <SETTING_8021x_USER_PRIVATE_KEY>Benutzer-Privatschlüssel</SETTING_8021x_USER_PRIVATE_KEY>
    <SETTING_8021x_EAPOL_VERSION_ERR>Bitte EAPOL-Version auswählen.</SETTING_8021x_EAPOL_VERSION_ERR>
    <SETTING_8021x_USERNAME_ERR>Bitte Benutzernamen eingeben.</SETTING_8021x_USERNAME_ERR>
    <SETTING_8021x_PASSWORD_ERR>Bitte Benutzerpasswort eingeben.</SETTING_8021x_PASSWORD_ERR>
    <SETTING_8021x_MISS_CERTIFICATE>Fehler. Fehlende Zerifikate.</SETTING_8021x_MISS_CERTIFICATE>
    <SETTING_8021x_FILE_WARNING>Bitte Datei auswählen.</SETTING_8021x_FILE_WARNING>
    <SETTING_8021x_MISS_KEY>Fehler. Fehlender privater Benutzerschlüssel</SETTING_8021x_MISS_KEY>
    <SETTING_8021x_INSTALL_CA_CER>CA Zertifikat Upload</SETTING_8021x_INSTALL_CA_CER>
    <SETTING_8021x_INSTALL_USER_CER>Benutzer Zertifikat Upload</SETTING_8021x_INSTALL_USER_CER>
    <SETTING_8021x_INSTALL_USER_KEY>Privater Schlüssel Upload</SETTING_8021x_INSTALL_USER_KEY>
    <!-- ##### NETWORK - HTTPS PAGE ##### -->
    <MENU_NETWORK_HTTPS>HTTPS</MENU_NETWORK_HTTPS>
    <SETTING_HTTPS>HTTPS*</SETTING_HTTPS>
    <SETTING_HTTPS_CSR_MANAGEMENT>Zertifikatsregistrierungsanforderung (CSR) Management</SETTING_HTTPS_CSR_MANAGEMENT>
    <SETTING_HTTPS_COMMON_NAME>Allgemeiner Name</SETTING_HTTPS_COMMON_NAME>
    <SETTING_HTTPS_CREATE>Erstellen</SETTING_HTTPS_CREATE>
    <SETTING_HTTPS_CER_MANAGEMENT>Zertifikatmanagement</SETTING_HTTPS_CER_MANAGEMENT>
    <SETTING_HTTPS_CREATE_SELFSIGNED_CER>Selbst-Signiertes Zertifikat erstellen</SETTING_HTTPS_CREATE_SELFSIGNED_CER>
    <SETTING_HTTPS_CREATE_CSR_WARNING_1>Warnung! Alle HTTPS Dateien werden nach dem Erstellen des CSR Datei entfernt</SETTING_HTTPS_CREATE_CSR_WARNING_1>
    <SETTING_HTTPS_CREATE_CSR_WARNING_2>Wollen Sie eine CSR Datei erstellen?</SETTING_HTTPS_CREATE_CSR_WARNING_2>
    <SETTING_HTTPS_CREATE_CSR>Erstellen Zertifikatsregistrierungsanforderung</SETTING_HTTPS_CREATE_CSR>
    <SETTING_HTTPS_COUNTRY>Land</SETTING_HTTPS_COUNTRY>
    <SETTING_HTTPS_STATE_PROVINCE>Staat oder Provinz</SETTING_HTTPS_STATE_PROVINCE>
    <SETTING_HTTPS_LOCALITY_CITY>Region oder Stadt</SETTING_HTTPS_LOCALITY_CITY>
    <SETTING_HTTPS_COMPANY>Firma</SETTING_HTTPS_COMPANY>
    <SETTING_HTTPS_ORGANIZATION>Organisations Unit</SETTING_HTTPS_ORGANIZATION>
    <SETTING_HTTPS_PRIVACY_KEY_LENGTH>Länge Privater Schlüssel</SETTING_HTTPS_PRIVACY_KEY_LENGTH>
    <SETTING_HTTPS_COUNTRY_DISCRIPTION>Benutzen Sie 2 Buchstaben Code ohne Punkte für Land. Z.B. DE oder CH</SETTING_HTTPS_COUNTRY_DISCRIPTION>
    <SETTING_HTTPS_STATE_PROVINCE_DISCRIPTION>Kürzen Sie die Provinz nicht ab. Z.B. Californien für CA</SETTING_HTTPS_STATE_PROVINCE_DISCRIPTION>
    <SETTING_HTTPS_LOCALITY_CITY_DISCRIPTION>Kürzen Sie die Stadt nicht ab. Z.B. Saint Louis für St</SETTING_HTTPS_LOCALITY_CITY_DISCRIPTION>
    <SETTING_HTTPS_COMPANY_DISCRIPTION>Firmenname, nur 0-9, a-z, A-Z Zeichen erlaubt</SETTING_HTTPS_COMPANY_DISCRIPTION>
    <SETTING_HTTPS_ORGANIZATION_DISCRIPTION>Der Name der Abteilung oder Organisation, die die Anfrage stellt. 0-9, a-z, A-Z sind erlaubt</SETTING_HTTPS_ORGANIZATION_DISCRIPTION>
    <SETTING_HTTPS_COMMON_NAME_DISCRIPTION>Der Host und Domain Name. Folgende Form "www.firma.com" oder "firma.com"</SETTING_HTTPS_COMMON_NAME_DISCRIPTION>
    <SETTING_HTTPS_BITS>Bits</SETTING_HTTPS_BITS>
    <SETTING_HTTPS_PROPERTIES>Eigenschaften</SETTING_HTTPS_PROPERTIES>
    <SETTING_HTTPS_INSTALL_SIGNED_CER>Unterzeichnetes Zertifikat installieren</SETTING_HTTPS_INSTALL_SIGNED_CER>
    <SETTING_HTTPS_CER_FILE>Zertifikat Datei</SETTING_HTTPS_CER_FILE>
    <SETTING_HTTPS_CER_FILE_ERR>Fehler. Zertifikat Datei</SETTING_HTTPS_CER_FILE_ERR>
    <SETTING_HTTPS_CER_VALIDITY>Zertifikat Gültigkeit</SETTING_HTTPS_CER_VALIDITY>
    <SETTING_HTTPS_CSR_PROPERTIES>Zertifikat Anforderung Eigenschaften</SETTING_HTTPS_CSR_PROPERTIES>
    <SETTING_HTTPS_CER_PROPERTIES>Zertifikat Eigenschaften</SETTING_HTTPS_CER_PROPERTIES>
    <SETTING_HTTPS_VALIDITY_DISCRIPTION>(1-9999 Tage). Die Gültigkeit des Zertifikats</SETTING_HTTPS_VALIDITY_DISCRIPTION>
    <!-- ##### NETWORK - LINK SPEED AND DUPLEX PAGE ##### -->
    <SETTING_LINK_SPEED_AND_DUPLEX>Speed &amp; Duplex</SETTING_LINK_SPEED_AND_DUPLEX>
    <!-- ## use SETTING_LINK_SPEED_WAN_SPEED translation to SETTING_LINK_SPEED_AND_DUPLEX -->
    <SETTING_LINK_SPEED_WAN_SPEED>Speed &amp; Duplex</SETTING_LINK_SPEED_WAN_SPEED>
    <!-- ##### IP SETTINGS - CONNECTION TYPE PAGE ##### -->
    <SETTING_CONNECTION_TYPE>Verbindungstyp*</SETTING_CONNECTION_TYPE>
    <SETTING_CONNECTION_TYPE_DYNAMIC_IP_ADDRESS>Dynamische IP-Adresse</SETTING_CONNECTION_TYPE_DYNAMIC_IP_ADDRESS>
    <SETTING_CONNECTION_TYPE_USE_HOSTNAME>Hostname des Benutzers</SETTING_CONNECTION_TYPE_USE_HOSTNAME>
    <SETTING_CONNECTION_TYPE_STATIC_IP_ADDRESS>Statische IP-Adresse</SETTING_CONNECTION_TYPE_STATIC_IP_ADDRESS>
    <SETTING_CONNECTION_TYPE_IP_ADDRESS>IP-Adresse</SETTING_CONNECTION_TYPE_IP_ADDRESS>
    <SETTING_CONNECTION_TYPE_SUBNET_MASK>Subnet-Maske</SETTING_CONNECTION_TYPE_SUBNET_MASK>
    <SETTING_CONNECTION_TYPE_ISP_GATEWAY>Gateway</SETTING_CONNECTION_TYPE_ISP_GATEWAY>
    <SETTING_CONNECTION_TYPE_PPPOE>PPPoE</SETTING_CONNECTION_TYPE_PPPOE>
    <SETTING_CONNECTION_TYPE_USER_NAME>Benutzername</SETTING_CONNECTION_TYPE_USER_NAME>
    <SETTING_CONNECTION_TYPE_PASSWORD>Passwort</SETTING_CONNECTION_TYPE_PASSWORD>
    <SETTING_CONNECTION_TYPE_STATIC_IP_ERR>Ungültige IP-Adresse</SETTING_CONNECTION_TYPE_STATIC_IP_ERR>
    <SETTING_CONNECTION_TYPE_SUBNET_MASK_ERR>Ungültige Subnet-Maske</SETTING_CONNECTION_TYPE_SUBNET_MASK_ERR>
    <SETTING_CONNECTION_TYPE_ISP_GATEWAY_ERR>IP-Adresse und Gateway nicht im selben Subnet.</SETTING_CONNECTION_TYPE_ISP_GATEWAY_ERR>
    <!-- ##### IP SETTINGS - DNS PAGE ##### -->
    <SETTING_DNS>DNS</SETTING_DNS>
    <SETTING_DNS_PRIMARY_DNS_SERVER>Primary DNS Server</SETTING_DNS_PRIMARY_DNS_SERVER>
    <SETTING_DNS_SECONDARY_DNS_SERVER>Secondary DNS Server</SETTING_DNS_SECONDARY_DNS_SERVER>
    <SETTING_DNS_PRIMARY_DNS_SERVER_ERR>Fehler. Ungültige Primary DNS Server-Einstellungen.</SETTING_DNS_PRIMARY_DNS_SERVER_ERR>
    <SETTING_DNS_SECONDARY_DNS_SERVER_ERR>Fehler. Ungültige Secondary DNS Server-Einstellungen.</SETTING_DNS_SECONDARY_DNS_SERVER_ERR>
    <!-- ##### IP SETTINGS - DDNS PAGE ##### -->
    <SETTING_DDNS>DDNS</SETTING_DDNS>
    <SETTING_DDNS_SERVICE_ISP>als Service/Protokollreferenz</SETTING_DDNS_SERVICE_ISP>
    <SETTING_DDNS_HOST_NAME>Hostname</SETTING_DDNS_HOST_NAME>
    <SETTING_DDNS_USER_NAME>Benutzername</SETTING_DDNS_USER_NAME>
    <SETTING_DDNS_PASSWORD>Passwort</SETTING_DDNS_PASSWORD>
    <SETTING_DDNS_HOST_NAME_ERR>Bitte Hostnamen eingeben.</SETTING_DDNS_HOST_NAME_ERR>
    <!-- ##### Camera Option PAGE ##### -->
    <SETTING_HIGH_FRAME_MODE>High Frame Modus</SETTING_HIGH_FRAME_MODE>
    <!-- ##### VIDEO AND AUDIO - VIDEO PAGE (STREAM MODE) ##### -->
    <SETTING_VIDEO_STREAM_MODE>Stream-Modus</SETTING_VIDEO_STREAM_MODE>
    <SETTING_VIDEO_FISHEYE_OPTION>Kamera-Optionen</SETTING_VIDEO_FISHEYE_OPTION>
    <SETTING_VIDEO_CURRENT_STREAM_ID>Stream-ID</SETTING_VIDEO_CURRENT_STREAM_ID>
    <SETTING_VIDEO_MOUNTING_TYPE>Befestigungsart</SETTING_VIDEO_MOUNTING_TYPE>
    <SETTING_VIDEO_CEIL_ANGLE>Neigungswinkel</SETTING_VIDEO_CEIL_ANGLE>
    <SETTING_VIDEO_INSTALLATION_ANGLE>Physikalischer Installationswinkel</SETTING_VIDEO_INSTALLATION_ANGLE>
    <SETTING_VIDEO_ROTATION_DEGREE>Rotations-Stufen pro Klick</SETTING_VIDEO_ROTATION_DEGREE>
    <!-- ##### VIDEO AND AUDIO - VIDEO PAGE (TAB) ##### -->
    <SETTING_VIDEO_ADVANCE>Video</SETTING_VIDEO_ADVANCE>
    <SETTING_VIDEO_IMAGE>Bild</SETTING_VIDEO_IMAGE>
    <SETTING_VIDEO_DAYNIGHT>Tag &amp; Nacht</SETTING_VIDEO_DAYNIGHT>
    <SETTING_VIDEO_MD>Bewegungserkennung</SETTING_VIDEO_MD>
    <SETTING_VIDEO_COMPRESSION>Komprimierung</SETTING_VIDEO_COMPRESSION>
    <SETTING_VIDEO_EXP_WB>Belichtung/Weißabgleich</SETTING_VIDEO_EXP_WB>
    <!-- ##### VIDEO AND AUDIO - VIDEO PAGE (Image) ##### -->
    <SETTING_VIDEO_VIDEO_FLIPPING>Video drehen</SETTING_VIDEO_VIDEO_FLIPPING>
    <SETTING_VIDEO_VIDEO_MIRROR>Video spiegeln</SETTING_VIDEO_VIDEO_MIRROR>
    <SETTING_VIDEO_BRIGHTNESS>Helligkeit</SETTING_VIDEO_BRIGHTNESS>
    <SETTING_VIDEO_CONTRAST>Kontrast</SETTING_VIDEO_CONTRAST>
    <SETTING_VIDEO_SATURATION>Sättigung</SETTING_VIDEO_SATURATION>
    <SETTING_VIDEO_SHARPNESS>Schärfe</SETTING_VIDEO_SHARPNESS>
    <SETTING_DNR>Digitale Rauschunterdrückung</SETTING_DNR>
    <SETTING_VIDEO_3DNR>3D-Rauschred.</SETTING_VIDEO_3DNR>
    <SETTING_VIDEO_EDGE>Kantenverbessern</SETTING_VIDEO_EDGE>
    <SETTING_VIDEO_EXDR_LEVLE>WDR-Ziel-Level</SETTING_VIDEO_EXDR_LEVLE>
    <SETTING_VIDEO_EXDR>WDR</SETTING_VIDEO_EXDR>
    <SETTING_VIDEO_DEFOG>Anti-Beschlag</SETTING_VIDEO_DEFOG>
    <SETTING_RESTORE_IMAGE>Bildeinstellungen auf Standard setzen</SETTING_RESTORE_IMAGE>
    <IMAGE_STABILIZATION>Bild Stabilisierung</IMAGE_STABILIZATION>
    <!-- ##### VIDEO AND AUDIO - VIDEO PAGE (DAY/NIGHT) ##### -->
    <SETTING_VIDEO_DN_MODE>Tag&amp;Nacht-Modus</SETTING_VIDEO_DN_MODE>
    <SETTING_VIDEO_DN_IRLED>IR LED Control</SETTING_VIDEO_DN_IRLED>
    <SETTING_IRLED_STRENGTH_LEVEL>IR LED Stärke Level</SETTING_IRLED_STRENGTH_LEVEL>
    <SETTING_IRLED_COVERAGE>Abdeckung</SETTING_IRLED_COVERAGE>
    <SETTING_VIDEO_N_GAIN_THRESHOLD>Wechsel von Tag- zu Nachtmodus</SETTING_VIDEO_N_GAIN_THRESHOLD>
    <!-- ##### VIDEO AND AUDIO - VIDEO PAGE (MOTION) ##### -->
    <SETTING_VIDEO_MD_STREAM_1>Bewegungserkennung (Nur Media 1)</SETTING_VIDEO_MD_STREAM_1>
    <SETTING_VIDEO_MD_ENABLED>Aktiviert</SETTING_VIDEO_MD_ENABLED>
    <SETTING_VIDEO_REGION>Nereich</SETTING_VIDEO_REGION>
    <SETTING_VIDEO_MOTION_ENABLE>Aktiviert</SETTING_VIDEO_MOTION_ENABLE>
    <SETTING_VIDEO_SENSITIVITY>Empfindlichkeit</SETTING_VIDEO_SENSITIVITY>
    <SETTING_VIDEO_TRIGGER_INTERVAL>Auslösungsintervall [s]</SETTING_VIDEO_TRIGGER_INTERVAL>
    <SETTING_VIDEO_TRIGGER_THRESHOLE>Auslöseschwelle</SETTING_VIDEO_TRIGGER_THRESHOLE>
    <SETTING_MOTION_DETECTION_WARNING>Bewegungserkennung in Stream 1 muss H.264 oder MPEG-4 nutzen.</SETTING_MOTION_DETECTION_WARNING>
    <SETTING_VIDEO_PRIOTITY>Priorität</SETTING_VIDEO_PRIOTITY>
    <SETTING_VIDEO_PRESET_ERR>Bitte stellen Sie Presetpunkte in Live-Seite</SETTING_VIDEO_PRESET_ERR>
    <HINT_MD_EXCLIDED_REGION>* : Bewegungserkennung außerhalb des nereichs 1 ~ 9</HINT_MD_EXCLIDED_REGION>
    <!-- ##### VIDEO AND AUDIO - VIDEO PAGE (COMPRESSION) ##### -->
    <SETTING_VIDEO_TV>TV-Standard</SETTING_VIDEO_TV>
    <MENU_VIDEO_AND_AUDIO_MEDIA1>Stream 1</MENU_VIDEO_AND_AUDIO_MEDIA1>
    <SETTING_MEDIA_ENCODER_TYPE>Encoder-Typ</SETTING_MEDIA_ENCODER_TYPE>
    <SETTING_MEDIA_H264_PROFILE>H.264 Profil</SETTING_MEDIA_H264_PROFILE>
    <SETTING_MEDIA_RESOLUTION>Auflösung</SETTING_MEDIA_RESOLUTION>
    <SETTING_MEDIA_VGA_ASPECT_RATIO>VGA Bildverhältnis</SETTING_MEDIA_VGA_ASPECT_RATIO>
    <SETTING_MEDIA_FR>Bildrate</SETTING_MEDIA_FR>
    <SETTING_MEDIA_BITRATE_MODE>Video-Bitraten-Modus</SETTING_MEDIA_BITRATE_MODE>
    <SETTING_MEDIA_MAX_BIT_RATE>max. Bitrate Video</SETTING_MEDIA_MAX_BIT_RATE>
    <SETTING_MEDIA_BIT_RATE>Video-Bitrate</SETTING_MEDIA_BIT_RATE>
    <SETTING_MEDIA_QUALITY>Qualität</SETTING_MEDIA_QUALITY>
    <SETTING_MEDIA_GOP>GOP 1 I-frame /</SETTING_MEDIA_GOP>
    <SETTING_MEDIA_1>Stream 1</SETTING_MEDIA_1>
    <SETTING_MEDIA_2>Stream 2</SETTING_MEDIA_2>
    <SETTING_MEDIA_3>Stream 3</SETTING_MEDIA_3>
    <SETTING_MEDIA2_MSG>Streaming-Modus ist "Single Streaming", Media 2 deaktiviert.</SETTING_MEDIA2_MSG>
    <SETTING_MEDIA2_MASK_MSG>Warnung: Privacy Mask ist in Media 2 nicht verfügbar. Bitte deaktivieren Sie zuerst Privacy Mask.</SETTING_MEDIA2_MASK_MSG>
    <!-- ##### VIDEO AND AUDIO - VIDEO PAGE (EXPOSURE/WHITE BALANCE) ##### -->
    <SETTING_VIDEO_LINE_FREQUENCY>Netzfrequenz</SETTING_VIDEO_LINE_FREQUENCY>
    <SETTING_VIDEO_EXPOSURE_MODE>Belichtungsmodus</SETTING_VIDEO_EXPOSURE_MODE>
    <SETTING_VIDEO_SHUTTER_MODE>Blendenmodus</SETTING_VIDEO_SHUTTER_MODE>
    <SETTING_VIDEO_WB_MODE>Weißabgleich</SETTING_VIDEO_WB_MODE>
    <SETTING_VIDEO_R_GAIN>Rotwert</SETTING_VIDEO_R_GAIN>
    <SETTING_VIDEO_B_GAIN>Blauwert</SETTING_VIDEO_B_GAIN>
    <SETTING_VIDEO_WB_HOLD>Halten</SETTING_VIDEO_WB_HOLD>
    <SETTING_VIDEO_AGC_GAIN>AE Referenzziel</SETTING_VIDEO_AGC_GAIN>
    <SETTING_VIDEO_AUTO_SHUTTER_SPEED>Max.Blendengeschw.</SETTING_VIDEO_AUTO_SHUTTER_SPEED>
    <SETTING_VIDEO_EXPOSURE_GAIN>Belichtungswert</SETTING_VIDEO_EXPOSURE_GAIN>
    <SETTING_VIDEO_SHUTTER_SPEED>Blendengeschw.</SETTING_VIDEO_SHUTTER_SPEED>
    <SETTING_VIDEO_IRIS_CONTROL>Blendenkontrolle</SETTING_VIDEO_IRIS_CONTROL>
    <SETTING_VIDEO_MAX_IRIS>Max. Auto-IRIS</SETTING_VIDEO_MAX_IRIS>
    <SETTING_VIDEO_VIDEO_PIRIS>P-IRIS</SETTING_VIDEO_VIDEO_PIRIS>
    <!-- ##### VIDEO AND AUDIO - AUDIO PAGE ##### -->
    <SETTING_VIDEO_AUDIO>Audio</SETTING_VIDEO_AUDIO>
    <SETTING_VIDEO_AUDIO_IN>Audio-In</SETTING_VIDEO_AUDIO_IN>
    <SETTING_VIDEO_AUDIO_IN_SENSITITY>Audio-In-Empfindlichkeit</SETTING_VIDEO_AUDIO_IN_SENSITITY>
    <SETTING_VIDEO_AUDIO_OUT_VOLUME>Audio-Out-Lautstärke</SETTING_VIDEO_AUDIO_OUT_VOLUME>
    <SETTING_AUDIO_FORMAT>Audioformat</SETTING_AUDIO_FORMAT>
    <!-- ##### VIDEO AND AUDIO - OSD/PRIVACY MASK PAGE ##### -->
    <SETTING_VIDEO_PRIVACE_MASK>OSD/Privacy Mask</SETTING_VIDEO_PRIVACE_MASK>
    <SETTING_VIDEO_PRIVACE_MASK_OSD_REGION>Bereich</SETTING_VIDEO_PRIVACE_MASK_OSD_REGION>
    <SETTING_VIDEO_PRIVACE_MASK_OSD_TYPE>Typ</SETTING_VIDEO_PRIVACE_MASK_OSD_TYPE>
    <SETTING_VIDEO_PRIVACE_MASK_COLOR>Farbe</SETTING_VIDEO_PRIVACE_MASK_COLOR>
    <SETTING_VIDEO_OSD_TRANSPARENT>Transparent</SETTING_VIDEO_OSD_TRANSPARENT>
    <SETTING_VIDEO_OSD_POSITION>Position</SETTING_VIDEO_OSD_POSITION>
    <SETTING_VIDEO_OSD_STRING>Vordef. Texte</SETTING_VIDEO_OSD_STRING>
    <SETTING_VIDEO_OSD_FORMAT>Textformat</SETTING_VIDEO_OSD_FORMAT>
    <SETTING_VIDEO_OSD_FORMAT_NOTICE>Was ist das?</SETTING_VIDEO_OSD_FORMAT_NOTICE>
    <SETTING_VIDEO_PRIVACE_MASK_SETUP>Einstellung</SETTING_VIDEO_PRIVACE_MASK_SETUP>
    <SETTING_VIDEO_PRIVACE_MASK_WARN>Privat Zonen nicht überlappen</SETTING_VIDEO_PRIVACE_MASK_WARN>
    <SETTING_CHECK_LENTH_ALERT>Bitte nicht mehr als 63 Zeichen als OSD-Text eingeben.</SETTING_CHECK_LENTH_ALERT>
    <SETTING_CHECK_FORMAT_ALERT>Bitte nur  "A~Z","0-9","/",":","-"," " im OSD-Text eingeben.</SETTING_CHECK_FORMAT_ALERT>
    <!-- ##### EVENT - EVENT SERVER PAGE ##### -->
    <SETTING_EVENT_SERVER>Ereignis-Server</SETTING_EVENT_SERVER>
    <SETTING_EVENT_SERVER_TYPE>Typ</SETTING_EVENT_SERVER_TYPE>
    <SETTING_EVENT_SERVER_NETWORK_ADDRESS>Netzwerkadresse</SETTING_EVENT_SERVER_NETWORK_ADDRESS>
    <SETTING_EVENT_SERVER_PORTS>Ports</SETTING_EVENT_SERVER_PORTS>
    <SETTING_EVENT_SERVER_USER_NAME>Benutzername</SETTING_EVENT_SERVER_USER_NAME>
    <!-- ##### EVENT - EVENT SERVER PAGE (FTP SERVER) ##### -->
    <SETTING_EVENT_SERVER_FTP>FTP-Server-Konfiguration</SETTING_EVENT_SERVER_FTP>
    <SETTING_EVENT_SERVER_FTP_NETWORK_ADDRESS>Netzwerkadresse</SETTING_EVENT_SERVER_FTP_NETWORK_ADDRESS>
    <SETTING_EVENT_SERVER_FTP_PORT>Netzwerk-Port</SETTING_EVENT_SERVER_FTP_PORT>
    <SETTING_EVENT_SERVER_FTP_NAME>Benutzername</SETTING_EVENT_SERVER_FTP_NAME>
    <SETTING_EVENT_SERVER_FTP_PASSWORD>Benutzerpasswort</SETTING_EVENT_SERVER_FTP_PASSWORD>
    <SETTING_EVENT_SERVER_FTP_MODE>Modus</SETTING_EVENT_SERVER_FTP_MODE>
    <SETTING_EVENT_SERVER_FTP_MAX_CONNECTION_TIME>Max. Verbindungszeit</SETTING_EVENT_SERVER_FTP_MAX_CONNECTION_TIME>
    <SETTING_EVENT_SERVER_FTP_TIME_MSG>Sekunden (0-60s)</SETTING_EVENT_SERVER_FTP_TIME_MSG>
    <SETTING_EVENT_PORT_NULL>Bitte Netzwerk-Port eingeben.</SETTING_EVENT_PORT_NULL>
    <SETTING_EVENT_PORT_ERR>Netzwerk-Port ist ungültig.</SETTING_EVENT_PORT_ERR>
    <SETTING_EVENT_ADDR_NULL>Bitte Benutzernamen eingeben.</SETTING_EVENT_ADDR_NULL>
    <SETTING_EVENT_NAME_NULL>Bitte Benutzerpasswort eingeben.</SETTING_EVENT_NAME_NULL>
    <!-- ##### EVENT - EVENT SERVER PAGE (FTP SERVER) ##### -->
    <SETTING_EVENT_SERVER_SMTP>SMTP-Server-Konfiguration</SETTING_EVENT_SERVER_SMTP>
    <SETTING_EVENT_SERVER_SMTP_PRIMARY>Primary SMTP-Konfiguration</SETTING_EVENT_SERVER_SMTP_PRIMARY>
    <SETTING_EVENT_SERVER_SMTP_AUTH_TYPE>Authentifizierungstyp</SETTING_EVENT_SERVER_SMTP_AUTH_TYPE>
    <SETTING_EVENT_SERVER_SMTP_NAME>Benutzername</SETTING_EVENT_SERVER_SMTP_NAME>
    <SETTING_EVENT_SERVER_SMTP_PASSWORD>Benutzerpasswort</SETTING_EVENT_SERVER_SMTP_PASSWORD>
    <SETTING_EVENT_SERVER_SMTP_EMAIL_ADDRESS>Email-Absender-Adresse</SETTING_EVENT_SERVER_SMTP_EMAIL_ADDRESS>
    <SETTING_EVENT_SERVER_SMTP_SERVER_ADDRESS>Netzwerkadresse</SETTING_EVENT_SERVER_SMTP_SERVER_ADDRESS>
    <SETTING_EVENT_SERVER_SMTP_SERVER_PORT>Netzwerk-Port</SETTING_EVENT_SERVER_SMTP_SERVER_PORT>
    <SETTING_EVENT_SERVER_SMTP_SERVER_POP3_PORT>POP3 Portnummer</SETTING_EVENT_SERVER_SMTP_SERVER_POP3_PORT>
    <SETTING_EVENT_SERVER_SMTP_MAX_CONNECTION_TIME>Max. Verbindungszeit</SETTING_EVENT_SERVER_SMTP_MAX_CONNECTION_TIME>
    <SETTING_EVENT_SERVER_SMTP_TIME_MSG>Sekunden (0-300s)</SETTING_EVENT_SERVER_SMTP_TIME_MSG>
    <SETTING_EVENT_SERVER_SMTP_SECONDARY>Secondary SMTP-Konfiguration</SETTING_EVENT_SERVER_SMTP_SECONDARY>
    <SETTING_SMTP_NAME_NULL1>Bitte Primary Benutzernamen eingeben.</SETTING_SMTP_NAME_NULL1>
    <SETTING_SMTP_PWD_NULL1>Bitte Primary Benutzepasswort eingeben.</SETTING_SMTP_PWD_NULL1>
    <SETTING_SMTP_EMAIL_ADDR_ERR1>Ungültige Primary Email-Absender-Adresse.</SETTING_SMTP_EMAIL_ADDR_ERR1>
    <SETTING_SMTP_SERVER_ADDR_NULL1>Bitte Primary Netzwerkadresse eingeben.</SETTING_SMTP_SERVER_ADDR_NULL1>
    <SETTING_SMTP_SERVER_PORT_NULL1>Bitte Primary Netzwerkport eingeben.</SETTING_SMTP_SERVER_PORT_NULL1>
    <SETTING_SMTP_SERVER_PORT_ERR1>Primary Netzwerk-Port ist ungültig.</SETTING_SMTP_SERVER_PORT_ERR1>
    <SETTING_SMTP_POP3_PORT_NULL1>Bitte Primary POP3 Portnummer angeben.</SETTING_SMTP_POP3_PORT_NULL1>
    <SETTING_SMTP_POP3_PORT_ERR1>Primary POP3 Portnummer ist ungültig.</SETTING_SMTP_POP3_PORT_ERR1>
    <SETTING_SMTP_NAME_NULL2>Bitte Secondary Benutzernamen eingeben.</SETTING_SMTP_NAME_NULL2>
    <SETTING_SMTP_PWD_NULL2>Bitte Secondary Benutzepasswort eingeben.</SETTING_SMTP_PWD_NULL2>
    <SETTING_SMTP_EMAIL_ADDR_ERR2>Ungültige Secondary Email-Absender-Adresse.</SETTING_SMTP_EMAIL_ADDR_ERR2>
    <SETTING_SMTP_SERVER_ADDR_NULL2>Bitte Secondary Netzwerkadresse eingeben.</SETTING_SMTP_SERVER_ADDR_NULL2>
    <SETTING_SMTP_SERVER_PORT_NULL2>Bitte Secondary Netzwerkport eingeben.</SETTING_SMTP_SERVER_PORT_NULL2>
    <SETTING_SMTP_SERVER_PORT_ERR2>Secondary Netzwerk-Port ist ungültig.</SETTING_SMTP_SERVER_PORT_ERR2>
    <SETTING_SMTP_POP3_PORT_NULL2>Bitte Secondary POP3 Portnummer angeben.</SETTING_SMTP_POP3_PORT_NULL2>
    <SETTING_SMTP_POP3_PORT_ERR2>Secondary POP3 Portnummer ist ungültig.</SETTING_SMTP_POP3_PORT_ERR2>
    <!-- ##### EVENT - EVENT SERVER PAGE (HTTP SERVER 1 AND 2) ##### -->
    <SETTING_EVENT_SERVER_HTTPD>HTTP Server-Konfiguration</SETTING_EVENT_SERVER_HTTPD>
    <SETTING_EVENT_SERVER_HTTPD_NAME>Benutzername</SETTING_EVENT_SERVER_HTTPD_NAME>
    <SETTING_EVENT_SERVER_HTTPD_PASSWORD>Benutzerpasswort</SETTING_EVENT_SERVER_HTTPD_PASSWORD>
    <SETTING_EVENT_SERVER_HTTPD_NETWORK_ADDRESS>Netzwerkadresse</SETTING_EVENT_SERVER_HTTPD_NETWORK_ADDRESS>
    <SETTING_EVENT_SERVER_HTTPD_PORT>Netzwerkport</SETTING_EVENT_SERVER_HTTPD_PORT>
    <SETTING_EVENT_SERVER_HTTPD_MAX_CONNECTION_TIME>Max. Verbindungszeit</SETTING_EVENT_SERVER_HTTPD_MAX_CONNECTION_TIME>
    <SETTING_EVENT_SERVER_HTTPD_TIME>Sekunden (0-60s)</SETTING_EVENT_SERVER_HTTPD_TIME>
    <SETTING_HTTPD_NAME_NULL>Bitte Benutzernamen eingeben.</SETTING_HTTPD_NAME_NULL>
    <SETTING_HTTPD_PWD_NULL>Bitte Benutzerpasswort eingeben.</SETTING_HTTPD_PWD_NULL>
    <SETTING_HTTPD_ADDR_NULL>Bitte Netzwerkadresse eingeben.</SETTING_HTTPD_ADDR_NULL>
    <SETTING_HTTPD_PORT_NULL>Bitte Netzwerk-Port eingeben.</SETTING_HTTPD_PORT_NULL>
    <SETTING_HTTPD_PORT_ERR>Netzwerkport ist ungültig.</SETTING_HTTPD_PORT_ERR>
    <!-- ##### EVENT - EVENT CONFIGURATION PAGE ##### -->
    <SETTING_EVENT_CONFIGURATOR>Ereignis-Konfiguration</SETTING_EVENT_CONFIGURATOR>
    <BUTTON_DIGITAL>Digitale Ein- und Ausgänge</BUTTON_DIGITAL>
    <BUTTON_NOTIFICATION>Benachrichtigungstext</BUTTON_NOTIFICATION>
    <BUTTON_UPLOAD_VIDEO_SNAPSHOT>Upload Video/Snaphot und Audio.</BUTTON_UPLOAD_VIDEO_SNAPSHOT>
    <BUTTON_SEND_URL>URL-Befehle senden</BUTTON_SEND_URL>
    <!-- ##### EVENT - EVENT CONFIGURATION PAGE (DIGITAL IO PORTS) ##### -->
    <SETTING_EVENT_CONFIGURATOR_DIGITAL>Digitale Ein- und Ausgänge</SETTING_EVENT_CONFIGURATOR_DIGITAL>
    <SETTING_EVENT_CONFIGURATOR_DIGITAL_INPUT_PORT>Digitaler Eingangs-Port</SETTING_EVENT_CONFIGURATOR_DIGITAL_INPUT_PORT>
    <SETTING_EVENT_CONFIGURATOR_PORT>Port</SETTING_EVENT_CONFIGURATOR_PORT>
    <SETTING_EVENT_CONFIGURATOR_ACTIVE_LEVEL>Aktiv-Level</SETTING_EVENT_CONFIGURATOR_ACTIVE_LEVEL>
    <SETTING_EVENT_CONFIGURATOR_DI_INTERVAL>Intervall (0-86400 Sekunden)</SETTING_EVENT_CONFIGURATOR_DI_INTERVAL>
    <SETTING_EVENT_CONFIGURATOR_DO_INTERVAL>Intervall* (0-86400 Sekunden)</SETTING_EVENT_CONFIGURATOR_DO_INTERVAL>
    <SETTING_EVENT_CONFIGURATOR_DI1>DI 1</SETTING_EVENT_CONFIGURATOR_DI1>
    <SETTING_EVENT_CONFIGURATOR_DI2>DI 2</SETTING_EVENT_CONFIGURATOR_DI2>
    <SETTING_EVENT_CONFIGURATOR_DI3>DI 3</SETTING_EVENT_CONFIGURATOR_DI3>
    <SETTING_EVENT_CONFIGURATOR_DI4>DI 4</SETTING_EVENT_CONFIGURATOR_DI4>
    <SETTING_EVENT_CONFIGURATOR_DIGITAL_OUTPUT_PORT>Digitaler Ausgangs-Port</SETTING_EVENT_CONFIGURATOR_DIGITAL_OUTPUT_PORT>
    <SETTING_EVENT_CONFIGURATOR_DO1>DO 1</SETTING_EVENT_CONFIGURATOR_DO1>
    <SETTING_EVENT_CONFIGURATOR_DO2>DO 2</SETTING_EVENT_CONFIGURATOR_DO2>
    <SETTING_EVENT_CONFIGURATOR_DIGITAL_HINT>* Wenn 0, wird der digitale Ausgangs-Port auf aktivem Level bleiben bis das verbundene Ereignis inaktiv wird.</SETTING_EVENT_CONFIGURATOR_DIGITAL_HINT>
    <!-- ##### EVENT - EVENT CONFIGURATION PAGE (NOTIFICATION MESSAGE) ##### -->
     <SETTING_EVENT_CONFIGURATOR_MSG>Benachrichtigungstext</SETTING_EVENT_CONFIGURATOR_MSG>
    <SETTING_EVENT_CONFIGURATOR_MSG_WARNING>Felder müssen ausgefüllt sein.</SETTING_EVENT_CONFIGURATOR_MSG_WARNING>
    <SETTING_EVENT_CONFIGURATOR_MSG_SEND_TO>Sende Nachricht an</SETTING_EVENT_CONFIGURATOR_MSG_SEND_TO>
    <SETTING_EVENT_CONFIGURATOR_MSG_EMAIL_ADDRESS>Email-Empfänger</SETTING_EVENT_CONFIGURATOR_MSG_EMAIL_ADDRESS>
    <SETTING_EVENT_CONFIGURATOR_MSG_EMAIL_ADDRESS_DESC>";" nutzen für mehrere Adressen</SETTING_EVENT_CONFIGURATOR_MSG_EMAIL_ADDRESS_DESC>
    <SETTING_EVENT_CONFIGURATOR_MSG_SUBJECT>Betreff</SETTING_EVENT_CONFIGURATOR_MSG_SUBJECT>
    <SETTING_EVENT_CONFIGURATOR_MSG_MESSAGE>Nachricht</SETTING_EVENT_CONFIGURATOR_MSG_MESSAGE>
    <SETTING_EVENT_CONFIGURATOR_MSG_CGI_SETTING>CGI-Pfad &amp; -Programm</SETTING_EVENT_CONFIGURATOR_MSG_CGI_SETTING>
    <SETTING_EVENT_CONFIGURATOR_MSG_CGI_SETTING_DESC>inkl. Pfad des CGI-Programms</SETTING_EVENT_CONFIGURATOR_MSG_CGI_SETTING_DESC>
    <SETTING_EVENT_CONFIGURATOR_MSG_URL_COMMAND>URL-Befehl </SETTING_EVENT_CONFIGURATOR_MSG_URL_COMMAND>
    <SETTING_EVENT_SUBJECT_NULL>Bitte Betreff eingeben.</SETTING_EVENT_SUBJECT_NULL>
    <SETTING_EVENT_EMAIL_RX_ADDR_NULL>Bitte Email-Empfänger eingeben.</SETTING_EVENT_EMAIL_RX_ADDR_NULL>
    <SETTING_EVENT_EMAIL_RX_ADDR_ERR>Ungültige Email-Adresse(n) in Nachricht</SETTING_EVENT_EMAIL_RX_ADDR_ERR>
    <SETTING_EVENT_MESSAGE_NULL>Bitte Nachricht eingeben.</SETTING_EVENT_MESSAGE_NULL>
    <SETTING_EVENT_CGI_PATH_NULL>Bitte CGI-Pfad &amp; -Programm eingeben.</SETTING_EVENT_CGI_PATH_NULL>
    <EVENT_ERROR_MESSAGE>Fehler. Ungültige Einstellungen.</EVENT_ERROR_MESSAGE>
    <EVENT_TEST_ERROR>Fehler. Ereignis-Server nicht korrekt eingestellt.</EVENT_TEST_ERROR>
    <!-- ##### EVENT - EVENT CONFIGURATION PAGE (UPLOAD VIDEO/AUDIO) ##### -->
    <SETTING_EVENT_CONFIGURATOR_UPLOAD>Upload Video/Snaphot und Audio</SETTING_EVENT_CONFIGURATOR_UPLOAD>
    <SETTING_EVENT_CONFIGURATOR_UPLOAD_NOAUDIO>Upload Video/Snaphot</SETTING_EVENT_CONFIGURATOR_UPLOAD_NOAUDIO>
    <SETTING_EVENT_CONFIGURATOR_UPLOAD_IMAGE_TYPE>Medientyp des Uploads</SETTING_EVENT_CONFIGURATOR_UPLOAD_IMAGE_TYPE>
    <SETTING_EVENT_CONFIGURATOR_UPLOAD_SNAPSHOT>Snapshot</SETTING_EVENT_CONFIGURATOR_UPLOAD_SNAPSHOT>
    <SETTING_EVENT_CONFIGURATOR_UPLOAD_VIDEO>Video</SETTING_EVENT_CONFIGURATOR_UPLOAD_VIDEO>
    <SETTING_EVENT_CONFIGURATOR_UPLOAD_SEND_MSG_TO>Medien-Upload nach</SETTING_EVENT_CONFIGURATOR_UPLOAD_SEND_MSG_TO>
    <SETTING_EVENT_CONFIGURATOR_UPLOAD_BUFFER_TIME>Vorpuffer-Dauer</SETTING_EVENT_CONFIGURATOR_UPLOAD_BUFFER_TIME>
    <SETTING_EVENT_PREBUF_TIME_MSG>(0-3 Sekunden)</SETTING_EVENT_PREBUF_TIME_MSG>
    <SETTING_EVENT_CONFIGURATOR_UPLOAD_TIME>Upload-Phase</SETTING_EVENT_CONFIGURATOR_UPLOAD_TIME>
    <SETTING_EVENT_UPLOAD_TIME_MSG>(0-86400 Sekunden)</SETTING_EVENT_UPLOAD_TIME_MSG>
    <SETTING_EVENT_CONFIGURATOR_UPLOAD_IMAGE_RATE>Bilder pro Upload-Phase</SETTING_EVENT_CONFIGURATOR_UPLOAD_IMAGE_RATE>
    <SETTING_EVENT_CONFIGURATOR_UPLOAD_IMAGE_RATE_DESC>(0 für maximale Anzahl an Bildern)</SETTING_EVENT_CONFIGURATOR_UPLOAD_IMAGE_RATE_DESC>
    <SETTING_EVENT_CONFIGURATOR_UPLOAD_FILE_NAME>Bilddatei-Name</SETTING_EVENT_CONFIGURATOR_UPLOAD_FILE_NAME>
    <SETTING_EVENT_CONFIGURATOR_UPLOAD_PATH>Upload-Pfad</SETTING_EVENT_CONFIGURATOR_UPLOAD_PATH>
    <SETTING_EVENT_FILENAME_PATH_RULE>Namensregeln</SETTING_EVENT_FILENAME_PATH_RULE>
    <SETTING_EVENT_CONFIGURATOR_UPLOAD_EMAIL_ADDRESS>Email-Empfänger</SETTING_EVENT_CONFIGURATOR_UPLOAD_EMAIL_ADDRESS>
    <SETTING_EVENT_CONFIGURATOR_UPLOAD_EMAIL_ADDRESS_DESC>";" nutzen für mehrere Adressen</SETTING_EVENT_CONFIGURATOR_UPLOAD_EMAIL_ADDRESS_DESC>
    <SETTING_EVENT_CONFIGURATOR_UPLOAD_SUBJECT>Betreff</SETTING_EVENT_CONFIGURATOR_UPLOAD_SUBJECT>
    <SETTING_EVENT_CONFIGURATOR_UPLOAD_VIDEO_SRC>Videoquelle</SETTING_EVENT_CONFIGURATOR_UPLOAD_VIDEO_SRC>
    <SETTING_EVENT_CONFIGURATOR_UPLOAD_CGI_SETTING>CGI-Pfad &amp; -Programm</SETTING_EVENT_CONFIGURATOR_UPLOAD_CGI_SETTING>
    <SETTING_EVENT_FILENAME_PATH_NULL>Bitte Bilddatei-Namen eingeben</SETTING_EVENT_FILENAME_PATH_NULL>
    <!-- ##### EVENT - EVENT CONFIGURATION PAGE (SEND URL COMMAND) ##### -->
    <SETTING_EVENT_CONFIGURATOR_CMD>URL-Befehle senden</SETTING_EVENT_CONFIGURATOR_CMD>
    <SETTING_EVENT_CONFIGURATOR_CMD_ENABLE>Sende Befehl 1 an</SETTING_EVENT_CONFIGURATOR_CMD_ENABLE>
    <SETTING_EVENT_CONFIGURATOR_CMD_ENABLE2>Sende Befehl 2 an</SETTING_EVENT_CONFIGURATOR_CMD_ENABLE2>
    <SETTING_EVENT_CONFIGURATOR_CMD_ENABLE3>Sende Befehl 3 an</SETTING_EVENT_CONFIGURATOR_CMD_ENABLE3>
    <SETTING_EVENT_CONFIGURATOR_CMD_EVENT_TRIGGER>Befehl als Ereignis ist ausgelöst.</SETTING_EVENT_CONFIGURATOR_CMD_EVENT_TRIGGER>
    <SETTING_EVENT_CONFIGURATOR_CMD_EVENT_TRIGGER_DESC>inkl. Pfad des CGI-Programms (max. 119 Zeichen)</SETTING_EVENT_CONFIGURATOR_CMD_EVENT_TRIGGER_DESC>
    <SETTING_EVENT_CONFIGURATOR_CMD_EVENT_INACTIVE>Befehl als Ereignis wird inaktiv.</SETTING_EVENT_CONFIGURATOR_CMD_EVENT_INACTIVE>
    <SETTING_EVENT_CONFIGURATOR_CMD_EVENT_INACTIVE_DESC>inkl. Pfad des CGI-Programms (max. 119 Zeichen)</SETTING_EVENT_CONFIGURATOR_CMD_EVENT_INACTIVE_DESC>
    <SETTING_EVENT_CMD_NULL>Bitte URL-Befehl eingeben</SETTING_EVENT_CMD_NULL>
    <!-- ##### EVENT - EVENT LIST PAGE ##### -->
    <SETTING_EVENT_LIST>Ereignisliste</SETTING_EVENT_LIST>
    <SETTING_EVENT_LIST_ID>ID</SETTING_EVENT_LIST_ID>
    <SETTING_EVENT_LIST_WEEKDAY>Wochentag</SETTING_EVENT_LIST_WEEKDAY>
    <SETTING_EVENT_LIST_START>Beginn</SETTING_EVENT_LIST_START>
    <SETTING_EVENT_EVENT_DURATION>Dauer</SETTING_EVENT_EVENT_DURATION>
    <SETTING_EVENT_SERVER_EVENT_SOURCE>Quelle</SETTING_EVENT_SERVER_EVENT_SOURCE>
    <SETTING_EVENT_SERVER_EVENT_ACTION>Aktion</SETTING_EVENT_SERVER_EVENT_ACTION>
    <!-- ##### EVENT - EVENT LIST PAGE (EVENT RULE) ##### -->
    <SETTING_EVENT_LIST_CYCLE_TIME>Aktiv am</SETTING_EVENT_LIST_CYCLE_TIME>
    <SETTING_EVENT_LIST_MON>Mon</SETTING_EVENT_LIST_MON>
    <SETTING_EVENT_LIST_TUE>Die</SETTING_EVENT_LIST_TUE>
    <SETTING_EVENT_LIST_WED>Mi</SETTING_EVENT_LIST_WED>
    <SETTING_EVENT_LIST_THR>Do</SETTING_EVENT_LIST_THR>
    <SETTING_EVENT_LIST_FRI>Fr</SETTING_EVENT_LIST_FRI>
    <SETTING_EVENT_LIST_SAT>Sa</SETTING_EVENT_LIST_SAT>
    <SETTING_EVENT_LIST_SUN>So</SETTING_EVENT_LIST_SUN>
    <SETTING_EVENT_LIST_START_TIME>Zeit</SETTING_EVENT_LIST_START_TIME>
    <SETTING_EVENT_LIST_DURATION>Dauer</SETTING_EVENT_LIST_DURATION>
    <SETTING_EVENT_LIST_DURATION_DESC>(max. 168 Stunden</SETTING_EVENT_LIST_DURATION_DESC>
    <SETTING_EVENT_LIST_TRIGGER_BY>Ausgelöst von</SETTING_EVENT_LIST_TRIGGER_BY>
    <SETTING_EVENT_LIST_ONCE_EVERY>Einmal alle</SETTING_EVENT_LIST_ONCE_EVERY>
    <SETTING_EVENT_MINUTE>Minuten</SETTING_EVENT_MINUTE>
    <SETTING_EVENT_LIST_TRIGGER_BY_ID>Ausgelöst von DI</SETTING_EVENT_LIST_TRIGGER_BY_ID>
    <SETTING_EVENT_LIST_DI1>DI 1</SETTING_EVENT_LIST_DI1>
    <SETTING_EVENT_LIST_DI2>DI 2</SETTING_EVENT_LIST_DI2>
    <SETTING_EVENT_LIST_DI3>DI 3</SETTING_EVENT_LIST_DI3>
    <SETTING_EVENT_LIST_DI4>DI 4</SETTING_EVENT_LIST_DI4>
    <SETTING_EVENT_LIST_TRIGGER_BY_MOTION>Ausgelöst von Bewegungserkennung</SETTING_EVENT_LIST_TRIGGER_BY_MOTION>
    <SETTING_EVENT_LIST_MD1>Bereich 1</SETTING_EVENT_LIST_MD1>
    <SETTING_EVENT_LIST_MD2>Bereich 2</SETTING_EVENT_LIST_MD2>
    <SETTING_EVENT_LIST_MD3>Bereich 3</SETTING_EVENT_LIST_MD3>
    <SETTING_EVENT_LIST_PIR>PIR Bewegungssensor</SETTING_EVENT_LIST_PIR>
    <SETTING_EVENT_LIST_RESPONSE>Antwort an</SETTING_EVENT_LIST_RESPONSE>
    <SETTING_EVENT_LIST_DIGITAL_OUTPUT>Digitaler Ausgang </SETTING_EVENT_LIST_DIGITAL_OUTPUT>
    <SETTING_EVENT_LIST_RSPDO1>DO 1</SETTING_EVENT_LIST_RSPDO1>
    <SETTING_EVENT_LIST_RSPDO2>DO 2</SETTING_EVENT_LIST_RSPDO2>
    <SETTING_EVENT_LIST_SEND_NOTIFICATION_MSG>Sende Benachrichtigungstext</SETTING_EVENT_LIST_SEND_NOTIFICATION_MSG>
    <SETTING_EVENT_LIST_RSPMSG1>Text 1</SETTING_EVENT_LIST_RSPMSG1>
    <SETTING_EVENT_LIST_RSPMSG2>Text 2</SETTING_EVENT_LIST_RSPMSG2>
    <SETTING_EVENT_LIST_RSPMSG3>Text 3</SETTING_EVENT_LIST_RSPMSG3>
    <SETTING_EVENT_LIST_UPLOAD_VIDEO_SNAPSHOP>Upload Video/Snapshot</SETTING_EVENT_LIST_UPLOAD_VIDEO_SNAPSHOP>
    <SETTING_EVENT_LIST_RSPIMG1>Bild 1</SETTING_EVENT_LIST_RSPIMG1>
    <SETTING_EVENT_LIST_RSPIMG2>Bild 2</SETTING_EVENT_LIST_RSPIMG2>
    <SETTING_EVENT_LIST_RSPIMG3>Bild 3</SETTING_EVENT_LIST_RSPIMG3>
    <SETTING_EVENT_LIST_CHANGE_MOTION>Wechsel Bew.erkennungsprofil</SETTING_EVENT_LIST_CHANGE_MOTION>
    <SETTING_EVENT_LIST_RSPMD1>Bereich 1</SETTING_EVENT_LIST_RSPMD1>
    <SETTING_EVENT_LIST_RSPMD2>Bereich 2</SETTING_EVENT_LIST_RSPMD2>
    <SETTING_EVENT_LIST_RSPMD3>Bereich 3</SETTING_EVENT_LIST_RSPMD3>
    <SETTING_EVENT_LIST_RSPPIR>PIR Bewegungssensor</SETTING_EVENT_LIST_RSPPIR>
    <SETTING_EVENT_LIST_SEND_URL_CMD>URL-Befehl senden</SETTING_EVENT_LIST_SEND_URL_CMD>
    <SETTING_EVENT_LIST_RSPCMD1>URL-Befehl 1</SETTING_EVENT_LIST_RSPCMD1>
    <SETTING_EVENT_LIST_RSPCMD2>URL-Befehl 2</SETTING_EVENT_LIST_RSPCMD2>
    <SETTING_EVENT_LIST_RSPCMD3>URL-Befehl 3</SETTING_EVENT_LIST_RSPCMD3>
    <SETTING_EVENT_LIST_DN_MODE>In Tag/Nacht-Modus wechseln</SETTING_EVENT_LIST_DN_MODE>
    <SETTING_EVENT_LIST_RSPNIGHT>NACHT</SETTING_EVENT_LIST_RSPNIGHT>
    <SETTING_EVENT_LIST_RSPDAY>TAG</SETTING_EVENT_LIST_RSPDAY>
    <!-- ##### EVENT - MANUAL EVENT PAGE ##### -->
    <SETTING_EVENT_MANUAL>Man. Ereignis</SETTING_EVENT_MANUAL>
    <SETTING_EVENT_MANUAL_TRIGGERED>Kann manuell ausgelöst werden.</SETTING_EVENT_MANUAL_TRIGGERED>
    <!-- ##### SYSTEM - USER ACCOUNT PAGE ##### -->
    <SETTING_USER_ACCOUNT_SETTING>Benutzerkonto</SETTING_USER_ACCOUNT_SETTING>
    <SETTING_USER>Benutzer</SETTING_USER>
    <SETTING_USER_ACCOUNT>Benutzerkonto</SETTING_USER_ACCOUNT>
    <SETTING_USER_PASSWORD>Passwort</SETTING_USER_PASSWORD>
    <SETTING_USER_ACCOUNT_ROOT>Root</SETTING_USER_ACCOUNT_ROOT>
    <SETTING_USER_LEVEL>Benutzer-Level</SETTING_USER_LEVEL>
    <SETTING_ROOT_ACCOUNT_NULL>Root-Konto ist leer.</SETTING_ROOT_ACCOUNT_NULL>
    <SETTING_ROOT_PASSWORD_NULL>Root-Passwort ist leer.</SETTING_ROOT_PASSWORD_NULL>
    <SETTING_USER_ACCOUNT_NULL>Benutzerkonto ist leer.</SETTING_USER_ACCOUNT_NULL>
    <SETTING_USER_PASSWORD_NULL>Benutzerpasswort ist leer.</SETTING_USER_PASSWORD_NULL>
    <SETTING_ROOT_USER_ACCOUNT_ERR>Benutzername und Root-Name darf nicht gleich sein.</SETTING_ROOT_USER_ACCOUNT_ERR>
    <SETTING_GUEST_PREVIEW>Live Ansicht ohne Benutzername und Passwort</SETTING_GUEST_PREVIEW>
    <!-- ##### SYSTEM - SYSTEM INFO PAGE ##### -->
    <SETTING_SYSTEM_INFO>Systeminformation</SETTING_SYSTEM_INFO>
    <SETTING_SYSTEM_INFO1>Systeminformation:</SETTING_SYSTEM_INFO1>
    <SETTING_WAN_STATUS>WAN-Status:</SETTING_WAN_STATUS>
    <SETTING_SYSTEM_LOG>System-Log:</SETTING_SYSTEM_LOG>
    <CONFIG_FILE>Konfigurationsdatei:</CONFIG_FILE>
    <GET_CONFIG_01>Parameter dieses Gerätes und derzeitige Einstellungen.</GET_CONFIG_01>
    <GET_CONFIG_02>Bei Supportkontakt stets Server-Report beifügen.</GET_CONFIG_02>
    <GET_CONFIG_03>Lizenzen von Drittparteien.</GET_CONFIG_03>
    <BUTTON_PARAMETER_INFO>Parameter-Liste</BUTTON_PARAMETER_INFO>
    <BUTTON_GET_SERVER_REPORT>Server-Report</BUTTON_GET_SERVER_REPORT>
    <BUTTON_SOFTWARE_LICENSES>Lizenz anzeigen.</BUTTON_SOFTWARE_LICENSES>
    <!-- ##### SYSTEM - FACTORY DEFAULT PAGE ##### -->
    <SETTING_FACTORY_DEFAULT>Werkseinstellung</SETTING_FACTORY_DEFAULT>
    <SETTING_FACTORY_DEFAULT_CONFIG>Netzwerkeinstellungen und HTTP/HTTPS Port bewahren.</SETTING_FACTORY_DEFAULT_CONFIG>
    <SETTING_ALL_FACTORY_DEFAULT_CONFIG>Auf Werkseinstellungen zurücksetzen</SETTING_ALL_FACTORY_DEFAULT_CONFIG>
    <SETTING_FACTORY_DEFAULT_ALERT>Alle Einstellungen auf Standardwerte und Neustart. Fortfahren?</SETTING_FACTORY_DEFAULT_ALERT>
    <!-- ##### SYSTEM - FIRMWARE UPLOAD PAGE ##### -->
    <SETTING_SYSTEM_FIRMWARE_UPGRADE>Firmware-Upload</SETTING_SYSTEM_FIRMWARE_UPGRADE>
    <SETTING_SYSTEM_FIRMWARE_UPGRADE_CONFIRM>Neue Firmware hochladen?</SETTING_SYSTEM_FIRMWARE_UPGRADE_CONFIRM>
    <SETTING_SYSTEM_FIRMWARE_UPGRADE_FIRMWARE>Firmware:</SETTING_SYSTEM_FIRMWARE_UPGRADE_FIRMWARE>
    <!-- ##### SYSTEM - SAVE AND REBOOT PAGE ##### -->
    <SETTING_SYSTEM_REBOOT>Sichern &amp; Neustart</SETTING_SYSTEM_REBOOT>
    <SETTING_SYSTEM_REBOOT_STRING>Bitte "Übernehmen" klicken, um alle Einstellungen zu sichern und neuzustarten.</SETTING_SYSTEM_REBOOT_STRING>
    <SETTING_SYSTEM_REBOOT_WAIT>Bitte warten Sie 30 Sekunden für den System-Neustart. Das Fenster wird in 3 Sekunden schließen.</SETTING_SYSTEM_REBOOT_WAIT>
    <!-- ##### PTZ - PTZ PANEL ##### -->
    <SETTING_CHANNEL_PTZ_ADDR>Video Channel's PTZ Address</SETTING_CHANNEL_PTZ_ADDR>
    <SETTING_PTZ_ADDRESS>PTZ Address</SETTING_PTZ_ADDRESS>
    <PTZ_ADDR>Adresse</PTZ_ADDR>
    <PTZ_PAN_SPEED>Schwenkgeschw.</PTZ_PAN_SPEED>
    <PTZ_TILT_SPEED>Neigegeschw.</PTZ_TILT_SPEED>
    <PTZ_PAN_TILT_SPEED>Schwenkgeschw./Neigegeschw.</PTZ_PAN_TILT_SPEED>
    <SETTING_VIDEO_PRESET>Preset</SETTING_VIDEO_PRESET>
    <SETTING_PTZ_SAVE_HOME>Derzeitige Position als Ausgangspunkt speichern</SETTING_PTZ_SAVE_HOME>
    <SETTING_PTZ_VENDOR>PTZ-Hersteller/-Protokoll</SETTING_PTZ_VENDOR>
    <SETTING_PTZ_ZOOM_CONTROL>Zoom-Steuerung</SETTING_PTZ_ZOOM_CONTROL>
    <SETTING_PTZ_CONTINUED_ZOOM>Stufenloses Zoomen</SETTING_PTZ_CONTINUED_ZOOM>
    <SETTING_PTZ_DIGITAL_ZOOM>Digitale Zoomen</SETTING_PTZ_DIGITAL_ZOOM>
    <SETTING_PTZ_STEPPED_ZOOM>Schrittweises Zoomen</SETTING_PTZ_STEPPED_ZOOM>
    <SETTING_PTZ_ROTATION>Achsendrehung</SETTING_PTZ_ROTATION>
    <SETTING_PTZ_FOCUS_CONTROL>Fokussteuerung</SETTING_PTZ_FOCUS_CONTROL>
    <SETTING_PTZ_FOCUS_CONTINUED>Stufenloses Fokussieren</SETTING_PTZ_FOCUS_CONTINUED>
    <SETTING_PTZ_FOCUS_STEPPED>Schrittweises Fokussieren</SETTING_PTZ_FOCUS_STEPPED>
    <SETTING_PTZ_PRESET_SET>Regeln</SETTING_PTZ_PRESET_SET>
    <SETTING_PTZ_PRESET_GOTO>Gehe zu</SETTING_PTZ_PRESET_GOTO>
    <SETTING_PTZ_TOUR_CURRENT>Steuerung von Touren</SETTING_PTZ_TOUR_CURRENT>
    <SETTING_PTZ_TOUR_EDIT>Tour editieren</SETTING_PTZ_TOUR_EDIT>
    <SETTING_PTZ_TOUR_PAN>Schwenk.</SETTING_PTZ_TOUR_PAN>
    <SETTING_PTZ_TOUR_TILT>Neigen</SETTING_PTZ_TOUR_TILT>
    <SETTING_PTZ_TOUR_PATH_LIST>Presetpunkte</SETTING_PTZ_TOUR_PATH_LIST>
    <SETTING_SELECT_PRESET_POINT>Wählen Sie einen Preset-Punkt</SETTING_SELECT_PRESET_POINT>
    <PTZ_AUTO_SPEED>Gerät passt Pan und Tilt Geschwindigkeit mit Zoom-Verhältnis</PTZ_AUTO_SPEED>
    <PTZ_AUTO_FLIP>Auto-Flip</PTZ_AUTO_FLIP>
    <PTZ_REFOCUS>Refokussieren</PTZ_REFOCUS>
    <PTZ_IDLE_POS_DESC>Nach Stillstandzeit zu einem Preset Punkt zurück kehren</PTZ_IDLE_POS_DESC>
    <PTZ_IDLE_TIME>Stillstandzeit</PTZ_IDLE_TIME>
    <PTZ_IDLE_POS>Rückkehr Position</PTZ_IDLE_POS>
    <PTZ_HOME_POS>Ausgangspunkt</PTZ_HOME_POS>
    <PTZ_PRESET_POINT>Preset Punkt</PTZ_PRESET_POINT>
    <PTZ_SCAN>Auto Scan</PTZ_SCAN>
    <PTZ_SCAN_CONTROL>Scan Kontrolle</PTZ_SCAN_CONTROL>
    <PTZ_SCAN_POINTS>Scan Punkte</PTZ_SCAN_POINTS>
    <PTZ_SCAN_ANTI_CLOCKWISE>Gegen Uhrzeigersinn</PTZ_SCAN_ANTI_CLOCKWISE>
    <PTZ_SCAN_CLOCKWISE>Uhrzeigersinn</PTZ_SCAN_CLOCKWISE>
    <PTZ_PARK_CONF_1>Nach</PTZ_PARK_CONF_1>
    <PTZ_PARK_CONF_2>sekunden zu Auto Scan zurück</PTZ_PARK_CONF_2>
    <ZOOM_RATIO_LIMIT>Max. Zoom Verhältnis</ZOOM_RATIO_LIMIT>
    <ZOOM_RATIO>Zoom Verhältnis</ZOOM_RATIO>
    <!-- ##### Local Storage ##### -->
    <MENU_STORAGE>Lokaler Speicher</MENU_STORAGE>
    <MENU_STORAGE_STATUS>Status</MENU_STORAGE_STATUS>
    <MENU_STORAGE_UTILITIES>Hilfsmittel</MENU_STORAGE_UTILITIES>
    <MENU_STORAGE_FILELIST>Datei Management</MENU_STORAGE_FILELIST>
    <SETTING_STORAGE_MEDIA_TYPE>Speichermedium Typ</SETTING_STORAGE_MEDIA_TYPE>
    <SETTING_STORAGE_CAPACITY>Kapazität</SETTING_STORAGE_CAPACITY>
    <SETTING_STORAGE_FREE>Frei</SETTING_STORAGE_FREE>
    <SETTING_STORAGE_TOTAL>Total</SETTING_STORAGE_TOTAL>
    <SETTING_STORAGE_PERCENTAGE_OF_USAGE>Prozent der Benutzung</SETTING_STORAGE_PERCENTAGE_OF_USAGE>
    <SETTING_STORAGE_FILE_SYSTEM>Dateisystem</SETTING_STORAGE_FILE_SYSTEM>
    <BUTTON_MOUNT>Mounten</BUTTON_MOUNT>
    <BUTTON_UNMOUNT>Unmounten</BUTTON_UNMOUNT>
    <BUTTON_FORMAT>Formatieren</BUTTON_FORMAT>
    <BUTTON_SCAN>Scan</BUTTON_SCAN>
    <SETTING_UTILITY_MOUNT_UMOUNT>Mount/Unmount Speichermedium</SETTING_UTILITY_MOUNT_UMOUNT>
    <SETTING_UTILITY_MOUNT>Mount Speichermedium</SETTING_UTILITY_MOUNT>
    <SETTING_UTILITY_UMOUNT>Unmount Speichermedium</SETTING_UTILITY_UMOUNT>
    <SETTING_UTILITY_FORMAT>Speichermedium formatieren</SETTING_UTILITY_FORMAT>
    <SETTING_UTILITY_SCAN>Speichermedium scannen</SETTING_UTILITY_SCAN>
    <SETTING_DISABLE_EVENTS>Fehler. Bitte deaktivieren Sie Event Funktionen, die mit Aufnahme verknüpft sind.</SETTING_DISABLE_EVENTS>
    <SETTING_STORAGE_UNMOUNT_ALERT1>Das Speichermedium wird unbenutzbar</SETTING_STORAGE_UNMOUNT_ALERT1>
    <SETTING_STORAGE_UNMOUNT_ALERT2>Soll das Speichermedium entfernt werden?</SETTING_STORAGE_UNMOUNT_ALERT2>
    <SETTING_STORAGE_MOUNT_MSG>Speichermedium wurde erfolgreich gemountet</SETTING_STORAGE_MOUNT_MSG>
    <SETTING_STORAGE_MOUNT_ERR_MSG>Fehler beim Mounten des Speichermediums (Bitte formatieren).</SETTING_STORAGE_MOUNT_ERR_MSG>
    <SETTING_STORAGE_UNMOUNT_MSG>Speichermedium kann nun entfernt werden</SETTING_STORAGE_UNMOUNT_MSG>
    <SETTING_STORAGE_UMOUNT_ERR_MSG>Speichermedium können nicht unmounted werden</SETTING_STORAGE_UMOUNT_ERR_MSG>
    <SETTING_STORAGE_FORMAT_ALERT1>Warnung! Die Daten gehen verloren</SETTING_STORAGE_FORMAT_ALERT1>
    <SETTING_STORAGE_FORMAT_ALERT2>Soll das Speichermedium formatiert werden?</SETTING_STORAGE_FORMAT_ALERT2>
    <SETTING_STORAGE_FORMAT_WAIT_MSG>Dies dauert ein paar Minuten. Bitte nicht neu starten oder das Gerät Stromlos machen</SETTING_STORAGE_FORMAT_WAIT_MSG>
    <SETTING_STORAGE_FORMAT_MSG>Speichermedium wurde erfolgreich formatiert</SETTING_STORAGE_FORMAT_MSG>
    <SETTING_STORAGE_FORMAT_ERR_MSG>Speichermeidum konnte nicht formatiert werden.</SETTING_STORAGE_FORMAT_ERR_MSG>
    <SETTING_STORAGE_SHOW_LOG>Protokoll zeigen</SETTING_STORAGE_SHOW_LOG>
    <BUTTON_CLOSE>schliessen</BUTTON_CLOSE>
    <SETTING_STORAGE_SCAN_WAIT_MSG>Dies dauert ein paar Minuten. Bitte nicht neu starten oder das Gerät Stromlos machen</SETTING_STORAGE_SCAN_WAIT_MSG>
    <SETTING_STORAGE_SCAN_MSG>Speichermedium wurde komplett gescannt</SETTING_STORAGE_SCAN_MSG>
    <SETTING_STORAGE_SCAN_ERR_MSG>Fehler beim Scannen der Speicherkarte</SETTING_STORAGE_SCAN_ERR_MSG>
    <SETTING_STORAGE_SETUP_MSG1>Alte Aufnahmen entfernen, wenn Speicherplatz gering wird</SETTING_STORAGE_SETUP_MSG1>
    <SETTING_STORAGE_SETUP_MSG2>Sende eine Benachrichtigung wenn Speicherplatz niedrig wird</SETTING_STORAGE_SETUP_MSG2>
    <SETTING_STORAGE_SETUP_MSG3>Speicherkapazität</SETTING_STORAGE_SETUP_MSG3>
    <SETTING_STORAGE_SETUP_HELP>Gerät informiert, wenn der Speicherplatz geringer als dieser Wert wird. Um diese Benachrchtigung zu erhalten , setzen Sie ein Event auf</SETTING_STORAGE_SETUP_HELP>
    <SETTING_STORAGE_SEARCH_BY_TIME>Suche Aufnhamen nach Zeit</SETTING_STORAGE_SEARCH_BY_TIME>
    <SETTING_STORAGE_SEARCH_TIME_PERIOD>Zeitabschnitt</SETTING_STORAGE_SEARCH_TIME_PERIOD>
    <SETTING_STORAGE_SEARCH_BY_EVENTS>Suche Aufnahmen nach ausgelösten Ereignissen</SETTING_STORAGE_SEARCH_BY_EVENTS>
    <SETTING_STORAGE_SEARCH_BY_DIS>DIs</SETTING_STORAGE_SEARCH_BY_DIS>
    <SETTING_STORAGE_SEARCH_BY_MD>Bewegung</SETTING_STORAGE_SEARCH_BY_MD>
    <SETTING_STORAGE_SEARCH_SCH>Zeitplan</SETTING_STORAGE_SEARCH_SCH>
    <SETTING_STORAGE_SEARCH_BY_READY>Fertig für Service</SETTING_STORAGE_SEARCH_BY_READY>
    <BUTTON_SEARCH>Suche</BUTTON_SEARCH>
    <SETTING_STORAGE_SEARCH_FILE_NAME>Dateiname</SETTING_STORAGE_SEARCH_FILE_NAME>
    <SETTING_STORAGE_SEARCH_LENGTH>Länge (min.)</SETTING_STORAGE_SEARCH_LENGTH>
    <SETTING_STORAGE_SEARCH_EVENTS>Ereignisse</SETTING_STORAGE_SEARCH_EVENTS>
    <DESC_STORAGE_EVENT_TITLE>Beschreibung der Ereignis Felder</DESC_STORAGE_EVENT_TITLE>
    <DESC_STORAGE_EVENT_1>Wenn der Aufnahmebefehl durch ein kontinuierlichches Aufnahmeereignis namens "Fertig für Service" ausgelöst wurde, listet die Firmware die DIs und Bewegungerkennungsstatus im "Events" field. Dies unterstützt den Benutzer bei der Suche nach einem spezifischen Event aus den Dateien der langen Aufzeichnungszeiträume.</DESC_STORAGE_EVENT_1>
    <DESC_STORAGE_EVENT_2>Wenn der Aufnahmebefehl durch ein spezielles Ereignis, wie z.B. DIs, Bewegungerkennungseinstellung oder scheduler, ausgelöst wurde, listet die Firmware nur die ausgelösten Ereignisse im "Events" Feld, die mit der gegebenen Aufnahmedatei verbunden sind.</DESC_STORAGE_EVENT_2>
    <!-- ##### Troubleshooting ##### -->
    <ERROR_FOUND_MSG>Probleme wurden erkannt. Bitte folgen Sie den Schritten:</ERROR_FOUND_MSG>
    <ERROR_STEP1>Schritt 1</ERROR_STEP1>
    <ERROR_STEP1_MSG>Laden sie das Protokoll herunter und senden es an den technischen Support</ERROR_STEP1_MSG>
    <ERROR_GET_LOG>Protokoll herunterladen</ERROR_GET_LOG>
    <ERROR_STEP2>Schritt 2</ERROR_STEP2>
    <ERROR_STEP2_MSG>Wählen Sie eines der folgenden Kommandos</ERROR_STEP2_MSG>
    <ERROR_CMD1>Direkt neu starten</ERROR_CMD1>
    <ERROR_CMD2>Werkseisntellungen laden und neustarten</ERROR_CMD2>
    <ERROR_CMD3>Werkseisntellungen laden aber Netzwerkeinstellungen behalten und neu starten</ERROR_CMD3>
    <ERROR_GO_CMD>Kommando</ERROR_GO_CMD>
    <ERROR_TITLE>Problembehebung</ERROR_TITLE>
    <ERROR_SEL_CMD>Wählen</ERROR_SEL_CMD>
    <!-- ##### Values in Settings ##### -->
    <!-- ##### Networking Settings ##### -->
    <SELECT_COMMON_ENABLED>Aktiviert</SELECT_COMMON_ENABLED>
    <SELECT_COMMON_DISABLED>Deaktiviert</SELECT_COMMON_DISABLED>
    <SELECT_TOS_MIN_DELAY>Verzögerung minimieren</SELECT_TOS_MIN_DELAY>
    <SELECT_TOS_MAX_THROUGHPUT>Durchsatz maximieren</SELECT_TOS_MAX_THROUGHPUT>
    <SELECT_TOS_MAX_RELIABILITY>Zuverlässigkeit maximieren</SELECT_TOS_MAX_RELIABILITY>
    <SELECT_TOS_NORMAL_SERVICE>Normaler Dienst</SELECT_TOS_NORMAL_SERVICE>
    <SELECT_IPFILTER_ALLOWED>erlauben</SELECT_IPFILTER_ALLOWED>
    <SELECT_IPFILTER_BLOCKED>blockieren</SELECT_IPFILTER_BLOCKED>
    <SELECT_SPEED_DUPLEX_AUTO>Automatisch erkennen</SELECT_SPEED_DUPLEX_AUTO>
    <SELECT_SPEED_DUPLEX_100M_FULL_DUPLEX>100Mbps/Full Duplex</SELECT_SPEED_DUPLEX_100M_FULL_DUPLEX>
    <SELECT_SPEED_DUPLEX_100M_HALF_DUPLEX>100Mbps/Half Duplex</SELECT_SPEED_DUPLEX_100M_HALF_DUPLEX>
    <SELECT_SPEED_DUPLEX_10M_FULL_DUPLEX>10Mbps/Full Duplex</SELECT_SPEED_DUPLEX_10M_FULL_DUPLEX>
    <SELECT_SPEED_DUPLEX_10M_HALF_DUPLEX>10Mbps/Half Duplex</SELECT_SPEED_DUPLEX_10M_HALF_DUPLEX>
    <!-- ##### Language Settings ##### -->
    <SELECT_LANGUAGE_ENGLISH>English</SELECT_LANGUAGE_ENGLISH>
    <SELECT_LANGUAGE_T_CHINESE>繁體中文</SELECT_LANGUAGE_T_CHINESE>
    <SELECT_LANGUAGE_S_CHINESE>简体中文</SELECT_LANGUAGE_S_CHINESE>
    <SELECT_LANGUAGE_JAPANESE>日本語</SELECT_LANGUAGE_JAPANESE>
    <SELECT_LANGUAGE_SPANISH>Español</SELECT_LANGUAGE_SPANISH>
    <SELECT_LANGUAGE_ITALIAN>Italiano</SELECT_LANGUAGE_ITALIAN>
    <SELECT_LANGUAGE_GERMAN>Deutsch</SELECT_LANGUAGE_GERMAN>
    <SELECT_LANGUAGE_PORTUGUESE>Portuguese</SELECT_LANGUAGE_PORTUGUESE>
    <SELECT_LANGUAGE_CZECH>Čeština</SELECT_LANGUAGE_CZECH>
    <SELECT_LANGUAGE_FRENCH>Français</SELECT_LANGUAGE_FRENCH>
    <SELECT_LANGUAGE_GREEK>Greek</SELECT_LANGUAGE_GREEK>
    <SELECT_LANGUAGE_DUTCH>Nederlands</SELECT_LANGUAGE_DUTCH>
    <SELECT_LANGUAGE_RUSSIAN>Русский</SELECT_LANGUAGE_RUSSIAN>
    <SELECT_LANGUAGE_TURKISH>Turkish</SELECT_LANGUAGE_TURKISH>
    <SELECT_LANGUAGE_INDONESIAN>Indosesian</SELECT_LANGUAGE_INDONESIAN>
    <SELECT_LANGUAGE_SWEDISH>Swedish</SELECT_LANGUAGE_SWEDISH>
    <SELECT_LANGUAGE_POLISH>Polski</SELECT_LANGUAGE_POLISH>
    <SELECT_LANGUAGE_ROMANIAN>Romana</SELECT_LANGUAGE_ROMANIAN>
    <SELECT_LANGUAGE_HUNGARIAN>Magyar</SELECT_LANGUAGE_HUNGARIAN>
    <SELECT_LANGUAGE_KOREAN>한국어</SELECT_LANGUAGE_KOREAN>
    <SELECT_LANGUAGE_THAILAND>ประเทศไทย</SELECT_LANGUAGE_THAILAND>
    <!-- ##### DateTime Settings ##### -->
    <SELECT_DATE_TIME_MINUS_1200>(GMT)-12:00(Eniwetok,Kwajaein)</SELECT_DATE_TIME_MINUS_1200>
    <SELECT_DATE_TIME_MINUS_1100>(GMT)-11:00(Midway lsl,Samoa)</SELECT_DATE_TIME_MINUS_1100>
    <SELECT_DATE_TIME_MINUS_1000>(GMT)-10:00(Hawaii,Aleutian lsl)</SELECT_DATE_TIME_MINUS_1000>
    <SELECT_DATE_TIME_MINUS_0930>(GMT)-09:30(Marquesas Isl.)</SELECT_DATE_TIME_MINUS_0930>
    <SELECT_DATE_TIME_MINUS_0900>(GMT)-09:00(Alaska)</SELECT_DATE_TIME_MINUS_0900>
    <SELECT_DATE_TIME_MINUS_0800>(GMT)-08:00(Las Vegas,San Francisco,Vancouver)</SELECT_DATE_TIME_MINUS_0800>
    <SELECT_DATE_TIME_MINUS_0700>(GMT)-07:00(Calgary,Denver,Salt Lake City)</SELECT_DATE_TIME_MINUS_0700>
    <SELECT_DATE_TIME_MINUS_0600>(GMT)-06:00(Chicago,Dallas,Mexico City)</SELECT_DATE_TIME_MINUS_0600>
    <SELECT_DATE_TIME_MINUS_0500>(GMT)-05:00(New York,Toronto,Washington DC,Cuba)</SELECT_DATE_TIME_MINUS_0500>
    <SELECT_DATE_TIME_MINUS_0430>(GMT)-04:30(Venezuela)</SELECT_DATE_TIME_MINUS_0430>
    <SELECT_DATE_TIME_MINUS_0400>(GMT)-04:00(Charlottetown,Chile,Manaus,Paraguay)</SELECT_DATE_TIME_MINUS_0400>
    <SELECT_DATE_TIME_MINUS_0330>(GMT)-03:30(Labrador, Newfoundland)</SELECT_DATE_TIME_MINUS_0330>
    <SELECT_DATE_TIME_MINUS_0300>(GMT)-03:00(Brazilia,Sao Paulo)</SELECT_DATE_TIME_MINUS_0300>
    <SELECT_DATE_TIME_MINUS_0200>(GMT)-02:00(Noronha,Mid-Atlantic)</SELECT_DATE_TIME_MINUS_0200>
    <SELECT_DATE_TIME_MINUS_0100>(GMT)-01:00(Azores,Cap Verde lsl)</SELECT_DATE_TIME_MINUS_0100>
    <SELECT_DATE_TIME_PLUS_0000>(GMT)+00:00(Dublin,Lisbon,London,Reykjavik)</SELECT_DATE_TIME_PLUS_0000>
    <SELECT_DATE_TIME_PLUS_0100>(GMT)+01:00(Amsterdam,Berlin,Rome,Stockholm)</SELECT_DATE_TIME_PLUS_0100>
    <SELECT_DATE_TIME_PLUS_0200>(GMT)+02:00(Athens,Egypt,Helsinki)</SELECT_DATE_TIME_PLUS_0200>
    <SELECT_DATE_TIME_PLUS_0300>(GMT)+03:00(Iraq,Moscow,Riyadh)</SELECT_DATE_TIME_PLUS_0300>
    <SELECT_DATE_TIME_PLUS_0330>(GMT)+03:30(Iran)</SELECT_DATE_TIME_PLUS_0330>
    <SELECT_DATE_TIME_PLUS_0400>(GMT)+04:00(Abu Dubai,Baku)</SELECT_DATE_TIME_PLUS_0400>
    <SELECT_DATE_TIME_PLUS_0430>(GMT)+04:30(Afghanistan)</SELECT_DATE_TIME_PLUS_0430>
    <SELECT_DATE_TIME_PLUS_0500>(GMT)+05:00(lslamabad,Karachi,Tashkent)</SELECT_DATE_TIME_PLUS_0500>
    <SELECT_DATE_TIME_PLUS_0530>(GMT)+05:30(India, Sri Lanka)</SELECT_DATE_TIME_PLUS_0530>
    <SELECT_DATE_TIME_PLUS_0545>(GMT)+05:45(Nepal)</SELECT_DATE_TIME_PLUS_0545>
    <SELECT_DATE_TIME_PLUS_0600>(GMT)+06:00(Novosibirsk,Omsk)</SELECT_DATE_TIME_PLUS_0600>
    <SELECT_DATE_TIME_PLUS_0630>(GMT)+06:30(Cocos (Keeling) Isl. Myanmar)</SELECT_DATE_TIME_PLUS_0630>
    <SELECT_DATE_TIME_PLUS_0700>(GMT)+07:00(Bangkok,Hanoi,Jakarta)</SELECT_DATE_TIME_PLUS_0700>
    <SELECT_DATE_TIME_PLUS_0800>(GMT)+08:00(Beijing,Hong Kong,Shanghai,Taipei)</SELECT_DATE_TIME_PLUS_0800>
    <SELECT_DATE_TIME_PLUS_0900>(GMT)+09:00(Osaka,Sapporo,Tokyo)</SELECT_DATE_TIME_PLUS_0900>
    <SELECT_DATE_TIME_PLUS_0930>(GMT)+09:30(Northern Territory,South Australia)</SELECT_DATE_TIME_PLUS_0930>
    <SELECT_DATE_TIME_PLUS_1000>(GMT)+10:00(Canberra,Hobart,Melbourne,Sydney)</SELECT_DATE_TIME_PLUS_1000>
    <SELECT_DATE_TIME_PLUS_1100>(GMT)+11:00(Solomon lsl)</SELECT_DATE_TIME_PLUS_1100>
    <SELECT_DATE_TIME_PLUS_1130>(GMT)+11:30(Norfolk Isl.)</SELECT_DATE_TIME_PLUS_1130>
    <SELECT_DATE_TIME_PLUS_1200>(GMT)+12:00(Auckland,Wellington)</SELECT_DATE_TIME_PLUS_1200>
    <SELECT_DATE_TIME_PLUS_1245>(GMT)+12:45(Chatham Isl.)</SELECT_DATE_TIME_PLUS_1245>
    <SELECT_DATE_TIME_PLUS_1300>(GMT)+13:00(Nukualofa)</SELECT_DATE_TIME_PLUS_1300>
    <SELECT_DATE_TIME_TYPE1>Typ 1</SELECT_DATE_TIME_TYPE1>
    <SELECT_DATE_TIME_TYPE2>Typ 2</SELECT_DATE_TIME_TYPE2>
    <SELECT_DATE_TIME_JAN>Jan</SELECT_DATE_TIME_JAN>
    <SELECT_DATE_TIME_FEB>Feb</SELECT_DATE_TIME_FEB>
    <SELECT_DATE_TIME_MAR>Mär</SELECT_DATE_TIME_MAR>
    <SELECT_DATE_TIME_APR>Apr</SELECT_DATE_TIME_APR>
    <SELECT_DATE_TIME_MAY>Mai</SELECT_DATE_TIME_MAY>
    <SELECT_DATE_TIME_JUN>Jun</SELECT_DATE_TIME_JUN>
    <SELECT_DATE_TIME_JUL>Jul</SELECT_DATE_TIME_JUL>
    <SELECT_DATE_TIME_AUG>Aug</SELECT_DATE_TIME_AUG>
    <SELECT_DATE_TIME_SEP>Sep</SELECT_DATE_TIME_SEP>
    <SELECT_DATE_TIME_OCT>Okt</SELECT_DATE_TIME_OCT>
    <SELECT_DATE_TIME_NOV>Nov</SELECT_DATE_TIME_NOV>
    <SELECT_DATE_TIME_DEC>Dez</SELECT_DATE_TIME_DEC>
    <SELECT_DATE_TIME_FIRST>Erster</SELECT_DATE_TIME_FIRST>
    <SELECT_DATE_TIME_SECOND>Zweiter</SELECT_DATE_TIME_SECOND>
    <SELECT_DATE_TIME_THIRD>Dritter</SELECT_DATE_TIME_THIRD>
    <SELECT_DATE_TIME_LAST>Letzter</SELECT_DATE_TIME_LAST>
    <SELECT_DATE_TIME_MON>Mon</SELECT_DATE_TIME_MON>
    <SELECT_DATE_TIME_TUE>Die</SELECT_DATE_TIME_TUE>
    <SELECT_DATE_TIME_WED>Mit</SELECT_DATE_TIME_WED>
    <SELECT_DATE_TIME_THU>Don</SELECT_DATE_TIME_THU>
    <SELECT_DATE_TIME_FRI>Fre</SELECT_DATE_TIME_FRI>
    <SELECT_DATE_TIME_SAT>Sam</SELECT_DATE_TIME_SAT>
    <SELECT_DATE_TIME_SUN>Son</SELECT_DATE_TIME_SUN>
    <SELECT_DATE_TIME_UPDATE_5MINS>5 Minuten</SELECT_DATE_TIME_UPDATE_5MINS>
    <SELECT_DATE_TIME_UPDATE_1HOUR>1 Stunde</SELECT_DATE_TIME_UPDATE_1HOUR>
    <SELECT_DATE_TIME_UPDATE_6HOURS>6 Stunden</SELECT_DATE_TIME_UPDATE_6HOURS>
    <SELECT_DATE_TIME_UPDATE_12HOURS>12 Stunden</SELECT_DATE_TIME_UPDATE_12HOURS>
    <SELECT_DATE_TIME_UPDATE_1DAY>1 Tag</SELECT_DATE_TIME_UPDATE_1DAY>
    <!-- ##### Video Settings ##### -->
    <SELECT_VIDEO_COMPRESS_CBR_MODE>Konstante Bitrate</SELECT_VIDEO_COMPRESS_CBR_MODE>
    <SELECT_VIDEO_COMPRESS_VBR_MODE>Variable Bitrate</SELECT_VIDEO_COMPRESS_VBR_MODE>
    <SELECT_VIDEO_COMPRESS_MAX_BITRATE_UNLIMITED>Unlimitiert</SELECT_VIDEO_COMPRESS_MAX_BITRATE_UNLIMITED>
    <SELECT_VIDEO_COMPRESS_QUALITY_HIGH>Hoch</SELECT_VIDEO_COMPRESS_QUALITY_HIGH>
    <SELECT_VIDEO_COMPRESS_QUALITY_MEDIUM>Medium</SELECT_VIDEO_COMPRESS_QUALITY_MEDIUM>
    <SELECT_VIDEO_COMPRESS_QUALITY_LOW>niedrig</SELECT_VIDEO_COMPRESS_QUALITY_LOW>
    <SELECT_VIDEO_COMPRESS_GOP_SECOND>Sekunde</SELECT_VIDEO_COMPRESS_GOP_SECOND>
    <SELECT_VIDEO_COMPRESS_GOP_FRAME>Frame</SELECT_VIDEO_COMPRESS_GOP_FRAME>
    <SELECT_VIDEO_H264_BASELINE>Baseline</SELECT_VIDEO_H264_BASELINE>
    <SELECT_VIDEO_H264_MAINPROFILE>Main Profile</SELECT_VIDEO_H264_MAINPROFILE>
    <SELECT_VIDEO_H264_HIGHPROFILE>High Profile</SELECT_VIDEO_H264_HIGHPROFILE>
    <SELECT_VIDEO_MOTION_RUNTIME_PROFILE>Laufzeit MD Profil</SELECT_VIDEO_MOTION_RUNTIME_PROFILE>
    <SELECT_VIDEO_MOTION_EVENT_PROFILE>Ereignis MD Profil</SELECT_VIDEO_MOTION_EVENT_PROFILE>
    <SELECT_VIDEO_DAYNIGHT_MODE_AUTO>Auto</SELECT_VIDEO_DAYNIGHT_MODE_AUTO>
    <SELECT_VIDEO_DAYNIGHT_MODE_DAY>Tag</SELECT_VIDEO_DAYNIGHT_MODE_DAY>
    <SELECT_VIDEO_DAYNIGHT_MODE_NIGHT>Nacht</SELECT_VIDEO_DAYNIGHT_MODE_NIGHT>
    <SELECT_VIDEO_EXPOSURE_MODE_AUTO>Auto</SELECT_VIDEO_EXPOSURE_MODE_AUTO>
    <SELECT_VIDEO_EXPOSURE_MODE_SHUTTER_PRIORITY>Blendenautomatik</SELECT_VIDEO_EXPOSURE_MODE_SHUTTER_PRIORITY>
    <SELECT_VIDEO_EXPOSURE_MODE_IRIS_PRIORITY>IRIS Priorität</SELECT_VIDEO_EXPOSURE_MODE_IRIS_PRIORITY>
    <SELECT_VIDEO_EXPOSURE_MODE_MANUAL>Manuell</SELECT_VIDEO_EXPOSURE_MODE_MANUAL>
    <SELECT_VIDEO_WB_MODE_AUTO>Auto</SELECT_VIDEO_WB_MODE_AUTO>
    <SELECT_VIDEO_WB_MODE_MANUAL>Manuell</SELECT_VIDEO_WB_MODE_MANUAL>
    <SELECT_OSD_TYPE_OSD>OSD</SELECT_OSD_TYPE_OSD>
    <SELECT_OSD_TYPE_PRIVACY_MASK>Privacy Mask</SELECT_OSD_TYPE_PRIVACY_MASK>
    <SELECT_OSD_TOP>Top</SELECT_OSD_TOP>
    <SELECT_OSD_BOTTOM>Boden</SELECT_OSD_BOTTOM>
    <SELECT_AUDIO_IN_SEN_HIGH>Hoch</SELECT_AUDIO_IN_SEN_HIGH>
    <SELECT_AUDIO_IN_SEN_LOW>Klein</SELECT_AUDIO_IN_SEN_LOW>
    <SELECT_VAG_ASPECT_RATIO_AUTO>Auto Erkennung</SELECT_VAG_ASPECT_RATIO_AUTO>
    <SELECT_VAG_ASPECT_RATIO_FIXED>4:3</SELECT_VAG_ASPECT_RATIO_FIXED>
    <SELECT_STREAMING_MODE_PANORAMA>Panoramic Anzeigemodus</SELECT_STREAMING_MODE_PANORAMA>
    <SELECT_STREAMING_MODE_EPTZ>ePTZ</SELECT_STREAMING_MODE_EPTZ>
    <SELECT_STREAMING_MODE_FISHEYE_VIEW>Fisheye Anzeigemodus</SELECT_STREAMING_MODE_FISHEYE_VIEW>
    <!-- ##### Event Settings ##### -->
    <SELECT_EVENT_FTP_MODE_PASSIVE>Passiv</SELECT_EVENT_FTP_MODE_PASSIVE>
    <SELECT_EVENT_FTP_MODE_ACTIVE>Aktiv</SELECT_EVENT_FTP_MODE_ACTIVE>
    <SELECT_EVENT_TRIGGERED_BY_SCH>Zeitplan</SELECT_EVENT_TRIGGERED_BY_SCH>
    <SELECT_EVENT_TRIGGERED_BY_DI>DIs</SELECT_EVENT_TRIGGERED_BY_DI>
    <SELECT_EVENT_TRIGGERED_BY_MD>Bewegung</SELECT_EVENT_TRIGGERED_BY_MD>
    <SELECT_EVENT_TRIGGERED_BY_NIGHT>In Nachtmodus geschaltet</SELECT_EVENT_TRIGGERED_BY_NIGHT>
    <SELECT_EVENT_TRIGGERED_BY_READY>Gerät komplett gestartet</SELECT_EVENT_TRIGGERED_BY_READY>
    <SELECT_EVENT_TRIGGERED_BY_STOP>Geräteneustart</SELECT_EVENT_TRIGGERED_BY_STOP>
    <SELECT_EVENT_TRIGGERED_BY_DISKLOW>Speicherplatz verbraucht</SELECT_EVENT_TRIGGERED_BY_DISKLOW>
    <SELECT_EVENT_TRIGGERED_BY_DISKERR>Schreibfehler</SELECT_EVENT_TRIGGERED_BY_DISKERR>
    <SELECT_EVENT_TRIGGERED_BY_DISKREMOVE>Speichermedium entfernt</SELECT_EVENT_TRIGGERED_BY_DISKREMOVE>
    <SELECT_EVENT_MEDIA_EMAIL>E-Mail</SELECT_EVENT_MEDIA_EMAIL>
    <SELECT_EVENT_MEDIA_FTP>DTP Server</SELECT_EVENT_MEDIA_FTP>
    <SELECT_EVENT_MEDIA_CGI_1>HTTP CGI 1</SELECT_EVENT_MEDIA_CGI_1>
    <SELECT_EVENT_MEDIA_CGI_2>HTTP CGI 2</SELECT_EVENT_MEDIA_CGI_2>
    <SELECT_EVENT_MEDIA_STORAGE>Speichermedium</SELECT_EVENT_MEDIA_STORAGE>
    <!-- PTZ Settings -->
    <SELECT_PTZ_AUTO_ZOOM>Auto Refokus nach Zoom</SELECT_PTZ_AUTO_ZOOM>
    <!-- WEB UI Hints -->
    <HINT_LIVEVIEW>Live Ansicht</HINT_LIVEVIEW>
    <HINT_SETUP>Kameraeinstellungen</HINT_SETUP>
    <HINT_VIEW_STREAM_1>Video Stream 1 anzeigen</HINT_VIEW_STREAM_1>
    <HINT_VIEW_STREAM_2>Video Stream 2 anzeigen</HINT_VIEW_STREAM_2>
    <HINT_FULL_SCREEN>Vollbild</HINT_FULL_SCREEN>
    <HINT_SNAPSHOT>Schnappschuss</HINT_SNAPSHOT>
    <SNAPSHOT_ERROR>Fehler. Schnappschuss</SNAPSHOT_ERROR>
    <HINT_AUDIO>Sprechen</HINT_AUDIO>
    <HINT_ZOOM_IN>Reinzoomen</HINT_ZOOM_IN>
    <HINT_ZOOM_OUT>Rauszoomen</HINT_ZOOM_OUT>
    <HINT_PTZ_ON>PTZ Steuerung öffnen</HINT_PTZ_ON>
    <HINT_PTZ_OFF>PTZ Steuerung schliessen</HINT_PTZ_OFF>
    <HINT_SELECT_DO>DO Ports wählen</HINT_SELECT_DO>
    <HINT_SET_DO_HIGH>DO Port auf High level setzen</HINT_SET_DO_HIGH>
    <HINT_SET_DO_LOW>DO Port auf Low Level setzen</HINT_SET_DO_LOW>
    <HINT_MANUAL_TRIGGER>Ereignis manuell auslösen</HINT_MANUAL_TRIGGER>
    <HINT_SET_PC_VOLUME>PC Lautsprecher setzen</HINT_SET_PC_VOLUME>
    <HINT_MINIATURE_FISHEYE_VIEW_WINDOW>Miniatur Fischaugen Fenster</HINT_MINIATURE_FISHEYE_VIEW_WINDOW>
    <HINT_VIEW_MODE_OPTIONS>Optionen Anzeigemodus</HINT_VIEW_MODE_OPTIONS>
    <HINT_EPTZ_VIEW_MODE>ePTZ Anzeigemodus</HINT_EPTZ_VIEW_MODE>
    <HINT_PANORAMA_VIEW_MODE>Panorama Anzeigemodus</HINT_PANORAMA_VIEW_MODE>
    <HINT_FISHEYE_VIEW_MODE>Fisheye Anzeigemodus</HINT_FISHEYE_VIEW_MODE>
    <!-- ERROR mesage of login name, password, URL -->
    <SETTING_NETWORK_NAME_ERR>
        Regel für Geräte Name.&#10;
        1. Nur A~Z, a~z, 0~9, Minus Zeichen (-) und Punkte (.) sind erlaubt.&#10;
        2. Kein leeres oder Space Zeichen als Teil des Namens benutzen.&#10;
        3. Der letzte Buchstabe darf kein Minus Zeichen oder Punkt sein.&#10;
        4. Das erste Zeichen darf ein Buchstabe oder Zahl sein. &#10;
        5. Eine leere Eingabe ist nicht erlaubt
    </SETTING_NETWORK_NAME_ERR>
    <SETTING_LOGIN_NAME_ERR>
        Regeln für den Login Namen&#10;
        1. Nur A~Z, a~z, 0~9, @, !, ^, $, Minus Zeichen (-) und Punkte (.) sind erlaubt.&#10;
        2. Das erste Zeichen darf nur A~Z, a~z oder 0~9 sein.
    </SETTING_LOGIN_NAME_ERR>
    <SETTING_LOGIN_PWD_ERR>
        Regeln für das Passwort&#10;
        1. Erlaubt sind 0~9 A~Z a~z&#10;
        2. Erlaubte Sonderzeichen ! $ ( ) * + - . ; &lt; = &gt; @ [ ] ^ - { } | ~ 
    </SETTING_LOGIN_PWD_ERR>
    <SETTING_GENERAL_URI_ERR>
        Regel für Geräte Name.&#10;
        1. Nur A~Z, a~z, 0~9, Minus Zeichen (-), Unterstrich (_), Punkt (.) und Space ( ) sind erlaubt.&#10;
        2. Das letzte Zeichen darf kein Minus Zeichen, Unterstrich, Punkt oder Space sein.&#10;
        3. Das erste Zeichen darf ein Buchstabe oder Zahl sein.&#10;
        4. Eine leere Eingabe ist erlaubt
    </SETTING_GENERAL_URI_ERR>
    <SETTING_PPPOE_NAME_ERR>
        Regeln für den Login Namen&#10;
        1. Erlaubt sind 0~9 A~Z a~z&#10;
        2. Erlaubte Sonderzeichen ! $ ( ) * + - . ; &lt; = &gt; @ [ ] ^ - { } | ~ 
    </SETTING_PPPOE_NAME_ERR>
    <SETTING_PLANET_NETWORK_ERR>
        1. 6~16 Zeichen&#10;
        2. Nur A~Z, a~z, 0~9, Minus Zeichen (-)&#10;
        3. Der letzte Buchstabe darf kein Minus&#10;
        4. Das erste Zeichen darf ein Buchstabe oder Zahl sein.
    </SETTING_PLANET_NETWORK_ERR>
    <SETTING_PLANET_NAME_PWD_ERR>
        1.6~16 Zeichen&#10;
        2.Nur A~Z, a~z, 0~9
    </SETTING_PLANET_NAME_PWD_ERR>
</LANG>